<?xml version="1.0" encoding="UTF-8"?>
<art orl="ja" trl="en">
<inf yea="">jawiki-20090527-pages-articles.xml</inf>
<tit>
<j>生野の変</j>
<e type="trans" ver="1">The Ikuno Incident</e>
<cmt></cmt>
<e type="trans" ver="2">The Ikuno Incident</e>
<cmt>修正なし</cmt>
<e type="check" ver="1">The Ikuno Incident</e>
<cmt>修正なし</cmt>
</tit>
<par id="1">
<sen id="1">
<j>生野の変（いくののへん）は、江戸時代後期の文久3年（1863年）10月に但馬国生野（兵庫県生野町）において尊皇攘夷派が挙兵した事件である。</j>
<e type="trans" ver="1">The Ikuno Incident was an incident that occurred when the &quot;Sonno Joi ha&quot; (supporters of the doctrine of restoring the emperor and expelling the barbarians) raised an army in Ikuno, Tajima Province (Ikuno City, Hyogo Prefecture) in the latter Edo period in October 1863.</e>
<cmt></cmt>
<e type="trans" ver="2">The Ikuno Incident was an incident that occurred when the Sonno Joi ha (supporters of the doctrine of restoring the emperor and expelling the barbarians) raised an army in Ikuno, Tajima Province (Ikuno City, Hyogo Prefecture) in the latter Edo period in October 1863.</e>
<cmt>原文にない記号は削除しました。</cmt>
<e type="check" ver="1">The Ikuno Incident was an incident that occurred when the Sonno Joi ha (supporters of the doctrine of restoring the emperor and expelling the barbarians) raised an army in Ikuno, Tajima Province (Ikuno City, Hyogo Prefecture) in the latter Edo period in October 1863.</e>
<cmt>修正なし</cmt>
</sen>
<sen id="2">
<j>生野の乱、生野義挙とも言う。</j>
<e type="trans" ver="1">It is also known as the Ikuno Rebellion or The Heroic Deeds at Ikuno.</e>
<cmt></cmt>
<e type="trans" ver="2">It is also known as the Ikuno Rebellion or the Heroic Deeds at Ikuno.</e>
<cmt>Theを小文字にしました。</cmt>
<e type="check" ver="1">It is also known as the Ikuno Rebellion or the Heroic Deeds at Ikuno.</e>
<cmt>修正なし</cmt>
</sen>
</par>
<par id="2">
<sen id="3">
<j>背景</j>
<e type="trans" ver="1">Background</e>
<cmt></cmt>
<e type="trans" ver="2">Background</e>
<cmt>修正なし</cmt>
<e type="check" ver="1">Background</e>
<cmt>修正なし</cmt>
</sen>
</par>
<par id="3">
<sen id="4">
<j>文久3年（1863年）8月、吉村寅太郎、松本奎堂、藤本鉄石ら尊攘派浪士の天誅組は孝明天皇の大和行幸の魁たらんと欲し、前侍従中山忠光を擁して大和国へ入り、8月17日に五條市代官所を襲撃して挙兵した。</j>
<e type="trans" ver="1">In August 1863 masterless samurai (roshi) who revered the emperor like Torataro YOSHIMURA, Keido MATSUMOTO, Tesseki FUJIMOTO and others of the Tenchugumi (Heavenly Avenging Force) raised an army in order to charge ahead of Emperor Komei&apos;s Imperial Trip to the Yamato Province, led by ex-chamberlain Tadamitsu NAKAYAMA they went to Yamato Province and attacked the magistrate&apos;s office in Gojo City on August 17.</e>
<cmt></cmt>
<e type="trans" ver="2">In August 1863, the Tenchugumi (Heavenly Avenging Force,) a group of masterless samurai (roshi) who revered the emperor like Torataro YOSHIMURA, Keido MATSUMOTO, and Tesseki FUJIMOTO, raised an army in order to charge ahead of Emperor Komei&apos;s Imperial Trip to the Yamato Province and, led by ex-chamberlain Tadamitsu NAKAYAMA, they went to Yamato Province and attacked the magistrate&apos;s office in Gojo City on August 17.</e>
<cmt>文法を修正しました。</cmt>
<e type="check" ver="1">In August 1863, the Tenchugumi (Heavenly Avenging Force,) a group of masterless samurai (roshi) who revered the emperor like Torataro YOSHIMURA, Keido MATSUMOTO, and Tesseki FUJIMOTO, raised an army in order to charge ahead of Emperor Komei&apos;s Imperial Trip to the Yamato Province and, led by ex-chamberlain Tadamitsu NAKAYAMA, they went to Yamato Province and attacked the magistrate&apos;s office in Gojo City on August 17.</e>
<cmt>修正なし</cmt>
</sen>
<sen id="5">
<j>代官所を占拠した天誅組は「御政府」を称して、五条天領を天朝直轄地と定めた（天誅組の変）。</j>
<e type="trans" ver="1">The Tenchugumi occupied the magistrate&apos;s office, calling themselves &quot;the government&quot; and decided that the land controlled by the shogunate was to be land controlled by the Imperial Court (Tenchugumi Rebellion).</e>
<cmt></cmt>
<e type="trans" ver="2">The Tenchugumi occupied the magistrate&apos;s office, calling themselves &apos;the government&apos; and decided that Gojo tenryo (directly controlled land by bakufu) should be controlled by the Imperial Court (Tenchugumi incident).</e>
<cmt>記号を修正しました。単語をリストに揃えました。</cmt>
<e type="check" ver="1">The Tenchugumi occupied the magistrate&apos;s office, calling themselves &apos;the government&apos; and decided that Gojo tenryo (directly controlled land by bakufu) should be controlled by the Imperial Court (Tenchugumi incident).</e>
<cmt>修正なし</cmt>
</sen>
</par>
<par id="4">
<sen id="6">
<j>天誅組の過激な行動を危惧した公卿三条実美は暴発を制止するべく、学習院出仕の平野国臣（福岡藩脱藩）を五条へ送った。</j>
<e type="trans" ver="1">The court noble Sanetomi SANJO fearing the radical actions of the Tenchugumi sent Kuniomi HIRANO (ex-Fukuoka), who attented the Gakushuin (the educational institution of the Imperial Court) to Gojo to keep things under control.</e>
<cmt>http://ja.wikipedia.org/wiki/学習院_(幕末維新期)</cmt>
<e type="trans" ver="2">The court noble Sanetomi SANJO, fearing the radical actions of the Tenchugumi, sent Kuniomi HIRANO (who had left Fukuoka Domain) who worked in the Gakushuin (the educational institution of the Imperial Court,) to Gojo to keep their movement under control.</e>
<cmt>文法を修正しました。</cmt>
<e type="check" ver="1">The court noble Sanetomi SANJO, fearing the radical actions of the Tenchugumi, sent Kuniomi HIRANO (who had left Fukuoka Domain) who worked in the Gakushuin (the educational institution of the Imperial Court,) to Gojo to keep their movement under control.</e>
<cmt>修正なし</cmt>
</sen>
</par>
<par id="5">
<sen id="7">
<j>その直後の8月18日、政局は一変する。</j>
<e type="trans" ver="1">Soon after that, on August 18, the political situation changed completely.</e>
<cmt></cmt>
<e type="trans" ver="2">Soon after that, on August 18, the political situation changed completely.</e>
<cmt>修正なし</cmt>
<e type="check" ver="1">Soon after that, on August 18, the political situation changed completely.</e>
<cmt>修正なし</cmt>
</sen>
<sen id="8">
<j>会津藩と薩摩藩が結んで孝明天皇を動かし、大和行幸の延期と長州藩の御門警護を解任してしまう（八月十八日の政変）。</j>
<e type="trans" ver="1">The Aizu clan and the Satsuma clan joined forces to influence the emperor, the Imperial Trip to the Yamato Province got postponed and the Choshu clan, who were guarding the Imperial gates, were dismissed (Coup of August 18).</e>
<cmt></cmt>
<e type="trans" ver="2">The Aizu Domain and the Satsuma Domain joined forces to influence the emperor to postpone the Imperial Trip to the Yamato Province and to dismiss the Choshu Domain, who were guarding the Imperial gates (Coup of August 18).</e>
<cmt>藩はDomainとしました。文法を修正しました。</cmt>
<e type="check" ver="1">The Aizu Domain and the Satsuma Domain joined forces to influence the emperor to postpone the Imperial Trip to the Yamato Province and to dismiss the Choshu Domain, who were guarding the Imperial gates (Coup of August 18).</e>
<cmt>修正なし</cmt>
</sen>
<sen id="9">
<j>情勢が不利になった長州藩は京都を退去し、三条実美ら攘夷派公卿7人も追放された（七卿落ち）。</j>
<e type="trans" ver="1">As the situation became unfavourable for the Choshu clan they left Kyoto and also seven court nobles of the &quot;Joi-ha&quot; (expel the barbarians) including Sanetomi SANJO were exiled from Kyoto (Shichikyou ochi).</e>
<cmt></cmt>
<e type="trans" ver="2">As the situation became unfavorable for the Choshu Domain, they left Kyoto and also seven court nobles of the Joi-ha (expel the barbarians) including Sanetomi SANJO were exiled from Kyoto (Shichikyou ochi.)</e>
<cmt>藩はDomainとしました。文法を修正しました。</cmt>
<e type="check" ver="1">As the situation became unfavorable for the Choshu Domain, they left Kyoto and also seven court nobles of the Joi-ha (expel the barbarians) including Sanetomi SANJO were exiled from Kyoto (Shichikyou ochi.)</e>
<cmt>修正なし</cmt>
</sen>
</par>
<par id="6">
<sen id="10">
<j>変事を知らない平野は19日に五条に到着して、天誅組首脳と会って意気投合するが、その直後に京で政局が一変してしまったことを知る。</j>
<e type="trans" ver="1">Hirano arrived in Gojo on the nineteenth, not knowing about the calamity, he met the leader of the Tenchugumi and found him a kindred spirit, but soon he heard about the sudden political change in Kyoto.</e>
<cmt></cmt>
<e type="trans" ver="2">Hirano arrived in Gojo on 19, not knowing about the calamity, he met the leader of the Tenchugumi and found him as kindred spirit, but soon he heard about the sudden political change in Kyoto.</e>
<cmt>文法を修正しました。</cmt>
<e type="check" ver="1">Hirano arrived in Gojo on 19, not knowing about the calamity, he met the leader of the Tenchugumi and found him as kindred spirit, but soon he heard about the sudden political change in Kyoto.</e>
<cmt>修正なし</cmt>
</sen>
<sen id="11">
<j>平野は巻き返しを図るべく大和国を去った。</j>
<e type="trans" ver="1">Hirano tried to recover from this setback and left Yamato.</e>
<cmt></cmt>
<e type="trans" ver="2">Hirano left Yamato to try to recover from this setback.</e>
<cmt>文法を修正しました。</cmt>
<e type="check" ver="1">Hirano left Yamato to try to recover from this setback.</e>
<cmt>修正なし</cmt>
</sen>
</par>
<par id="7">
<sen id="12">
<j>天誅組は十津川郷士を募兵して1000人余の兵力になるが、装備は貧弱なものだった。</j>
<e type="trans" ver="1">The Tenchugumi recruited samurai from the Totsugawa area and had more than one thousand men under arms, but were poorly equipped.</e>
<cmt></cmt>
<e type="trans" ver="2">The Tenchugumi recruited samurai from the Totsugawa area and had more than one thousand men under arms, but were poorly equipped.</e>
<cmt>修正なし</cmt>
<e type="check" ver="1">The Tenchugumi recruited samurai from the Totsugawa area and had more than one thousand men under arms, but were poorly equipped.</e>
<cmt>修正なし</cmt>
</sen>
<sen id="13">
<j>高取城攻略を図るが失敗した。</j>
<e type="trans" ver="1">An attempt to take Takatori castle failed.</e>
<cmt>一原文一訳文の例外対処</cmt>
<e type="trans" ver="2">Their attempt to take Takatori castle failed.</e>
<cmt>冠詞を修正しました。</cmt>
<e type="check" ver="1">Their attempt to take Takatori castle failed.</e>
<cmt>修正なし</cmt>
</sen>
<sen id="14">
<j>9月に入って周辺諸藩からの討伐を受け、多勢に無勢で各地で敗退し、9月27日に壊滅した。</j>
<e type="trans" ver="1">In September they were attacked by neighboring clans, greatly outnumbered, they were defeated at various places and were annihilated on September 27.</e>
<cmt>一原文一訳文の例外対処</cmt>
<e type="trans" ver="2">In September they were attacked by neighboring domain and, being greatly outnumbered, they were defeated at various places and were annihilated on September 27.</e>
<cmt>文法を修正しました。</cmt>
<e type="check" ver="1">In September they were attacked by neighboring domain and, being greatly outnumbered, they were defeated at various places and were annihilated on September 27.</e>
<cmt>修正なし</cmt>
</sen>
</par>
<par id="8">
<sen id="15">
<j>挙兵</j>
<e type="trans" ver="1">Raising an army</e>
<cmt></cmt>
<e type="trans" ver="2">Raising an army</e>
<cmt>修正なし</cmt>
<e type="check" ver="1">Raising an army</e>
<cmt>修正なし</cmt>
</sen>
<sen id="16">
<j>但馬国は小藩の豊岡藩、出石藩以外は天領が多くを占めていた。</j>
<e type="trans" ver="1">Most of the land in Tajima Province was directly controlled by the shogunate (tenryo), except the small domains of the Toyooka clan and the Izushi clan.</e>
<cmt></cmt>
<e type="trans" ver="2">Most of the land in Tajima Province was directly controlled by the shogunate (tenryo), except the small domains of the Toyooka and the Izushi.</e>
<cmt>clanは削除しました。</cmt>
<e type="check" ver="1">Most of the land in Tajima Province was directly controlled by the shogunate (tenryo), except the small domains of the Toyooka and the Izushi.</e>
<cmt>修正なし</cmt>
</sen>
<sen id="17">
<j>同国の生野銀山が有名だが、幕末の頃には産出量が減少し、山間部のこの土地の住民は困窮していた。</j>
<e type="trans" ver="1">The Ikuno Silver Mine in that same province is famous, but by the end of the Edo Period silver production had decreased and the residents of this mountainous region were poor.</e>
<cmt></cmt>
<e type="trans" ver="2">The Ikuno Silver Mine in the province is famous, but by the end of the Edo Period, silver production had decreased and the residents of this mountainous region were poor.</e>
<cmt>文法を修正しました。</cmt>
<e type="check" ver="1">The Ikuno Silver Mine in the province is famous, but by the end of the Edo Period, silver production had decreased and the residents of this mountainous region were poor.</e>
<cmt>修正なし</cmt>
</sen>
<sen id="18">
<j>生野天領では豪農の北垣国道が農兵を募って海防にあたるべしとする「農兵論」を唱え、生野奉行の川上猪太郎がこの動きに好意的なこともあって、攘夷の気風が強かった。</j>
<e type="trans" ver="1">The spirit of expulsion of foreigners was strong as the wealthy farmer Kunimichi KITAGAKI at Ikuno proclaimed the &quot;Noheiron&quot; (Farmers to the arms doctrine) which said that conscripted farmers should defend the coast and the magistrate of Ikuno Itaro KAWAKAMI also favored this movement.</e>
<cmt></cmt>
<e type="trans" ver="2">Xenophobia was strong in Ikuno tenryo, as the wealthy farmer Kunimichi KITAGAKI proclaimed the &apos;Noheiron&apos; (Farmers to the arms doctrine) which said that conscripted farmers should defend the coast and the magistrate of Ikuno Itaro KAWAKAMI favored this movement.</e>
<cmt>文法を修正しました。攘夷はxenophobiaに変えました。</cmt>
<e type="check" ver="1">Xenophobia was strong in Ikuno tenryo, as the wealthy farmer Kunimichi KITAGAKI proclaimed the &apos;Noheiron&apos; (Farmers to the arms doctrine) which said that conscripted farmers should defend the coast and the magistrate of Ikuno Itaro KAWAKAMI favored this movement.</e>
<cmt>修正なし</cmt>
</sen>
<sen id="19">
<j>薩摩藩脱藩の美玉三平（寺田屋事件で逃亡）は北垣と連携し、農兵の組織化を図っていた。</j>
<e type="trans" ver="1">Ex-Satsuma samurai Sanpei MITAMA, (who had escaped at the Teradaya Incident) cooperated with Kitagaki in planning to organize an army of conscripted farmers.</e>
<cmt></cmt>
<e type="trans" ver="2">Ex-Satsuma samurai Sanpei MITAMA (who had escaped from the Teradaya Incident) cooperated with Kitagaki in organizing an army of conscripted farmers.</e>
<cmt>文法を修正しました。余分なスペースを削除しました。</cmt>
<e type="check" ver="1">Ex-Satsuma samurai Sanpei MITAMA (who had escaped from the Teradaya Incident) cooperated with Kitagaki in organizing an army of conscripted farmers.</e>
<cmt>修正なし</cmt>
</sen>
</par>
<par id="9">
<sen id="20">
<j>平野は長州藩士野村靖、鳥取藩士松田正人らとともに但馬で声望の高い北垣と結び、生野での挙兵を計画。</j>
<e type="trans" ver="1">A plan was made to raise an army in Ikuno by Hirano who together with the feudal retainers Yasushi NOMURA of the Choshu Clan and Masata MATSUDA of the Tottori Clan joined Kitagaki, who was very popular in Tajima.</e>
<cmt></cmt>
<e type="trans" ver="2">A plan was made to raise an army in Ikuno by Hirano who together with the feudal retainers Yasushi NOMURA of the Choshu Domain and Masata MATSUDA of the Tottori Domain joined, Kitagaki who was very popular in Tajima.</e>
<cmt>文法を修正しました。</cmt>
<e type="check" ver="1">A plan was made to raise an army in Ikuno by Hirano who together with the feudal retainers Yasushi NOMURA of the Choshu Domain and Masata MATSUDA of the Tottori Domain joined, Kitagaki who was very popular in Tajima.</e>
<cmt>修正なし</cmt>
</sen>
<sen id="21">
<j>但馬に入った平野らは9月19日に豪農中島太郎兵衛の家で同志と会合を開き、10月10日をもって挙兵と定め、長門国三田尻に保護されている攘夷派七卿の誰かを迎え、また武器弾薬を長州から提供させる手はずを決定する。</j>
<e type="trans" ver="1">After Hirano arrived in Tajima, he held a meeting with his comrades at the house of the wealthy farmer Tarobee NAKAJIMA on September 19, where they decided to raise an army on October 10 and to arrange a supply of weapons and ammunition from Choshu.</e>
<cmt></cmt>
<e type="trans" ver="2">After Hirano arrived in Tajima, he held a meeting with his comrades at the house of the wealthy farmer Tarobee NAKAJIMA on September 19, where they decided to hail one of the seven Joi-ha nobles protected in Mitajiri, Nagato Province as leader and raise an army on October 10 and to arrange a supply of weapons and ammunition from Choshu.</e>
<cmt>「長門国三田尻に保護されている攘夷派七卿の誰かを迎え」の訳を補いました。</cmt>
<e type="check" ver="1">After Hirano arrived in Tajima, he held a meeting with his comrades at the house of the wealthy farmer Tarobee NAKAJIMA on September 19, where they decided to hail one of the seven Joi-ha nobles protected in Mitajiri, Nagato Province as leader and raise an army on October 10 and to arrange a supply of weapons and ammunition from Choshu.</e>
<cmt>修正なし</cmt>
</sen>
</par>
<par id="10">
<sen id="22">
<j>28日に平野と北垣は長州三田尻に入り、七卿や藩主世子毛利定広を交えた会合を持ち、公卿沢宣嘉を主将に迎えることを決めた。</j>
<e type="trans" ver="1">On the twenty-eighth Hirano and Kitagaki went to Mitajiri, Choshu Province where they conversed with the seven court nobles and the heir of the Choshu Clan Sadahiro MORI and decided to appoint court noble Nobuyoshi SAWA as commander-in-chief.</e>
<cmt></cmt>
<e type="trans" ver="2">On 28, Hirano and Kitagaki went to Mitajiri, Choshu Province where they conversed with the seven court nobles and the heir of the Choshu Domain Sadahiro MORI and decided to appoint court noble Nobuyoshi SAWA as commander-in-chief.</e>
<cmt>文法を修正しました。</cmt>
<e type="check" ver="1">On 28, Hirano and Kitagaki went to Mitajiri, Choshu Province where they conversed with the seven court nobles and the heir of the Choshu Domain Sadahiro MORI and decided to appoint court noble Nobuyoshi SAWA as commander-in-chief.</e>
<cmt>修正なし</cmt>
</sen>
<sen id="23">
<j>平野らは更に藩としての挙兵への同調を求めるが、藩首脳部は消極的だった。</j>
<e type="trans" ver="1">Hirano furthermore asked the clan to sanction their undertaking, but the leaders of the clan were reluctant.</e>
<cmt></cmt>
<e type="trans" ver="2">Hirano furthermore asked the domain to go along with their undertaking, but the leaders of the domain were reluctant.</e>
<cmt>sanctionは不適切だと思いましたので修正しました。</cmt>
<e type="check" ver="1">Hirano furthermore asked the domain to go along with their undertaking, but the leaders of the domain were reluctant.</e>
<cmt>修正なし</cmt>
</sen>
</par>
<par id="11">
<sen id="24">
<j>10月2日、平野と北垣は沢とともに三田尻を出立して船を用意し、河上弥市（元奇兵隊総管）ら尊攘浪士を加えた37人が出港した。</j>
<e type="trans" ver="1">On October 2, Hirano, Kitagaki and Sawa left Mitajiri and prepared a boat, thirty-seven roshi (masterless samurai) who revered the emperor, among them Yaichi KAWAKAMI (former administrator of the Kiheitai Army) set sail.</e>
<cmt></cmt>
<e type="trans" ver="2">On October 2, Hirano, Kitagaki and Sawa left Mitajiri and prepared a boat, thirty-seven roshi including Yaichi KAWAKAMI (former administrator of the Kiheitai Army,) who revered the emperor, set sail.</e>
<cmt>文法を修正しました。</cmt>
<e type="check" ver="1">On October 2, Hirano, Kitagaki and Sawa left Mitajiri and prepared a boat, thirty-seven roshi including Yaichi KAWAKAMI (former administrator of the Kiheitai Army,) who revered the emperor, set sail.</e>
<cmt>修正なし</cmt>
</sen>
<sen id="25">
<j>10月8日に一行は播磨国に上陸、生野へ向かった。</j>
<e type="trans" ver="1">On October 8 they landed in Harima and headed towards Ikuno.</e>
<cmt></cmt>
<e type="trans" ver="2">On October 8, they landed in Harima and headed towards Ikuno.</e>
<cmt>文法を修正しました。</cmt>
<e type="check" ver="1">On October 8, they landed in Harima and headed towards Ikuno.</e>
<cmt>修正なし</cmt>
</sen>
<sen id="26">
<j>一行は11日に生野の手前の延応寺に本陣を置いた。</j>
<e type="trans" ver="1">On the eleventh they arrived at Ikuno Eno Temple, which lies just before Ikuno, where they put up their headquarters.</e>
<cmt></cmt>
<e type="trans" ver="2">On October 11, they arrived at Eno-ji Temple, which lies just before Ikuno, where they put up their headquarter.</e>
<cmt>日付の修正をしました。</cmt>
<e type="check" ver="1">On October 11, they arrived at Eno-ji Temple, which lies just before Ikuno, where they put up their headquarter.</e>
<cmt>修正なし</cmt>
</sen>
<sen id="27">
<j>この時点で大和の天誅組は壊滅しており、挙兵中止も議論され、平野は中止を主張するが、天誅組の復讐をすべしとの河上ら強硬派が勝ち、挙兵は決行されることになった。</j>
<e type="trans" ver="1">The Tenchugumi in Yamato was annihilated by then and some argued to give up, but while Hirano insisted to postpone, the hard-liners like Kawakami, who wanted to take revenge for the Tenchugumi, won the argument and it was decided to raise an army.</e>
<cmt></cmt>
<e type="trans" ver="2">The Tenchugumi in Yamato was annihilated by then and some argued to give up, but while Hirano insisted to postpone, the hard-liners like Kawakami, who wanted to take revenge for the Tenchugumi, won the argument and it was decided to raise an army.</e>
<cmt>修正なし</cmt>
<e type="check" ver="1">The Tenchugumi in Yamato was annihilated by then and some argued to give up, but while Hirano insisted to postpone, the hard-liners like Kawakami, who wanted to take revenge for the Tenchugumi, won the argument and it was decided to raise an army.</e>
<cmt>修正なし</cmt>
</sen>
</par>
<par id="12">
<sen id="28">
<j>播磨口の番所は彼らを穏便に通し、12日未明に生野に入った。</j>
<e type="trans" ver="1">The guard house at Harimaguchi let them pass quietly and they arrived in Ikuno in the early morning of the twelfth.</e>
<cmt></cmt>
<e type="trans" ver="2">The guard house at Harimaguchi let them pass quietly and they arrived in Ikuno in the early morning of 12.</e>
<cmt>数字は数字のままとしました。</cmt>
<e type="check" ver="1">The guard house at Harimaguchi let them pass quietly and they arrived in Ikuno in the early morning of 12.</e>
<cmt>修正なし</cmt>
</sen>
<sen id="29">
<j>生野代官所は彼らの動きを当然察知していたが、代官の川上猪太郎が出張中なこともあり、代官所を無抵抗で平野らへ明け渡した。</j>
<e type="trans" ver="1">The magistrate&apos;s office in Ikuno was of course aware of their movement, but because the magistrate Itaro KAWAKAMI just happened to be on a tour of duty, they surrendered without resistance to Hirano.</e>
<cmt></cmt>
<e type="trans" ver="2">The magistrate&apos;s office in Ikuno was of course aware of their movement, but because the magistrate Itaro KAWAKAMI just happened to be on a tour of duty, they surrendered without resistance to Hirano.</e>
<cmt>修正なし</cmt>
<e type="check" ver="1">The magistrate&apos;s office in Ikuno was of course aware of their movement, but because the magistrate Itaro KAWAKAMI just happened to be on a tour of duty, they surrendered without resistance to Hirano.</e>
<cmt>修正なし</cmt>
</sen>
<sen id="30">
<j>藩と違い、天領の代官所は広い地域を支配している割には軍備が手薄であり、天誅組の挙兵の際も五条代官所は40人程の浪士に占領されている。</j>
<e type="trans" ver="1">Unlike a clan, a magistrate&apos;s office of a shogunal demesne controlled a wider area and armaments were relatively weak, in fact at the time when the Tenchugumi raised an army, the magistrate&apos;s office in Gojo was occupied by just about forty roshi.</e>
<cmt></cmt>
<e type="trans" ver="2">Unlike a domain, a magistrate&apos;s office of a shogunal demesne controlled a wider area and armaments were relatively weak, in fact at the time when the Tenchugumi raised an army, the magistrate&apos;s office in Gojo was occupied by just about forty roshi.</e>
<cmt>clan→domainに修正しました。</cmt>
<e type="check" ver="1">Unlike a domain, a magistrate&apos;s office of a shogunal demesne controlled a wider area and armaments were relatively weak, in fact at the time when the Tenchugumi raised an army, the magistrate&apos;s office in Gojo was occupied by just about forty roshi.</e>
<cmt>修正なし</cmt>
</sen>
</par>
<par id="13">
<sen id="31">
<j>壊滅</j>
<e type="trans" ver="1">Annihilation</e>
<cmt></cmt>
<e type="trans" ver="2">Annihilation</e>
<cmt>修正なし</cmt>
<e type="check" ver="1">Annihilation</e>
<cmt>修正なし</cmt>
</sen>
<sen id="32">
<j>平野、北垣らは「当役所」の名で沢宣嘉の告諭文を発して、天領一帯に募兵を呼びかけ、かねてより北垣が「農兵論」を唱えていたこともあり、その日正午には2000人もの農民が生野の町に群集した。</j>
<e type="trans" ver="1">Hirano, Katagi and others issued an official notice by Nobuyoshi SAWA under the name&quot; this public office&quot;, calling for recruits all over the shogunate&apos;s land and because Kitagaki had already advocated the &quot;farmers to arms doctrine&quot;, on that day at noon around two thousand farmers gathered in Ikuno town.</e>
<cmt></cmt>
<e type="trans" ver="2">Hirano, Kitagaki and others issued an official notice by Nobuyoshi SAWA under the name &apos;this public office,&apos; calling for recruits all over the shogunate&apos;s land and because Kitagaki had already been advocating the &apos;farmers to arms doctrine,&apos; around two thousand farmers gathered in Ikuno town at noon on that day.</e>
<cmt>語順を入れ替えました。</cmt>
<e type="check" ver="1">Hirano, Kitagaki and others issued an official notice by Nobuyoshi SAWA under the name &apos;this public office,&apos; calling for recruits all over the shogunate&apos;s land and because Kitagaki had already been advocating the &apos;farmers to arms doctrine,&apos; around two thousand farmers gathered in Ikuno town at noon on that day.</e>
<cmt>修正なし</cmt>
</sen>
</par>
<par id="14">
<sen id="33">
<j>天誅組の変の直後とあって、幕府側の動きは早く、代官所留守から通報を受けるや豊岡藩、出石藩、姫路藩が動き、挙兵の翌13日には出石藩兵900人と姫路藩兵1000人が生野へ出動している。</j>
<e type="trans" ver="1">This happened right after the Tenchugumi rebellion, so the reaction of the shogunate was quick, as soon as they received reports from the keeper of the magistrate&apos;s office they set the Toyooka Clan, the Izushi Clan and the Himeji Clan in motion, a day after the rising of the army on the thirteenth, nine hundred soldiers from the Toyooka Clan and one thousand soldiers from the Himeji Clan marched to Ikuno.</e>
<cmt></cmt>
<e type="trans" ver="2">This happened right after the Tenchugumi rebellion, so the reaction of the shogunate was quick, as soon as they received reports from the keeper of the magistrate&apos;s office, they set the Toyooka Domain, the Izushi Domain and the Himeji Domains, a day after the rising of the army on the thirteenth, nine hundred soldiers from the Toyooka Domain and one thousand soldiers from the Himeji Domain marched to Ikuno.</e>
<cmt>数字は数字のままに島s似た。</cmt>
<e type="check" ver="1">This happened right after the Tenchugumi rebellion, so the reaction of the shogunate was quick, as soon as they received reports from the keeper of the magistrate&apos;s office, they set the Toyooka Domain, the Izushi Domain and the Himeji Domains, a day after the rising of the army on the thirteenth, nine hundred soldiers from the Toyooka Domain and one thousand soldiers from the Himeji Domain marched to Ikuno.</e>
<cmt>修正なし</cmt>
</sen>
</par>
<par id="15">
<sen id="34">
<j>諸藩の素早い動きに対して、浪士たちからは早くも解散説が持ち上がった。</j>
<e type="trans" ver="1">The roshi already began talking about dissolution, because of those quick actions of the clans.</e>
<cmt></cmt>
<e type="trans" ver="2">The roshi already began talking about dissolution, because of those quick actions of the domains.</e>
<cmt>OK</cmt>
<e type="check" ver="1">The roshi already began talking about dissolution, because of those quick actions of the domains.</e>
<cmt>修正なし</cmt>
</sen>
<sen id="35">
<j>強硬論の平野、河上らに圧されて解散は思いとどまるが、13日夜に肝心の主将の沢宣嘉が解散派とともに本陣から脱走してしまった。</j>
<e type="trans" ver="1">Hard-liners like Hirano and Kawakami were pressured to dissolve the army but desisted, on the night on the thirteenth the crucial commander-in-chief Nobuyoshi SAWA together with the &quot;pro-dissolution-party&quot; fled from headquarters.</e>
<cmt>In 39 the text says Kawakami was a hard-liner and Hirano already wanted to postpone the whole action. And now in 51 Hirano became a hard-liner, who doesn&apos;t want to cancel the action. I think, that is a mistake in the text, but don&apos;t know if the weblinks are reliable sources. http://bakusiken.cool.ne.jp/ikunogikyo/hazin.html#Anchor-37082 http://www13.ocn.ne.jp/~dawn/tabi36tenchu.htm</cmt>
<e type="trans" ver="2">Dissolution of the army was desisted by the pressures from hard-liners like Hirano and Kawakami but the crucial commander-in-chief Nobuyoshi SAWA, together with the pro-dissolution-party, fled from the headquarter on the night of 13.</e>
<cmt>この状況での平野は解散に反対するという意味で強硬論だったので、正しいと思います。また、思いとどまらせたのが平野と河野ですので訳もその通りに変えました。</cmt>
<e type="check" ver="1">Dissolution of the army was desisted by the pressures from hard-liners like Hirano and Kawakami but the crucial commander-in-chief Nobuyoshi SAWA, together with the pro-dissolution-party, fled from the headquarter on the night of 13.</e>
<cmt>修正なし</cmt>
</sen>
<sen id="36">
<j>集まった農民たちは動揺する。</j>
<e type="trans" ver="1"></e>
<cmt></cmt>
<e type="trans" ver="2">Conscripted farmers got upset.</e>
<cmt>訳が漏れていましたので補いました。</cmt>
<e type="check" ver="1">Conscripted farmers got upset.</e>
<cmt>修正なし</cmt>
</sen>
</par>
<par id="16">
<sen id="37">
<j>妙見山に布陣していた河上は生野の町で闘死しようとするが、騙されたと怒った農民たちが「偽浪士」と罵って彼らに襲いかかった。</j>
<e type="trans" ver="1">Kawakami who was on Mount Myoken with his men for the battle formation, tried to die heroically in Ikuno Town, but the farmers, who thought they had been deceived, got angry, abused them as &quot;fake roshi&quot; and attacked them.</e>
<cmt></cmt>
<e type="trans" ver="2">Kawakami who was on Mt. Myoken with his men for the battle formation, tried to die heroically in Ikuno Town, but the farmers, who thought they had been deceived, got angry, execrated them as &apos;fake roshi&apos; and attacked them.</e>
<cmt>罵るの訳を修正しました。妙見山はMt. Myokenとしました。</cmt>
<e type="check" ver="1">Kawakami who was on Mt. Myoken with his men for the battle formation, tried to die heroically in Ikuno Town, but the farmers, who thought they had been deceived, got angry, execrated them as &apos;fake roshi&apos; and attacked them.</e>
<cmt>修正なし</cmt>
</sen>
<sen id="38">
<j>河上ら13人の浪士は妙見山に戻って自刃して果てる。</j>
<e type="trans" ver="1">Kawakami and thirteen roshi returned to Mount Myoken and committed suicide by the sword.</e>
<cmt></cmt>
<e type="trans" ver="2">Kawakami and thirteen roshi returned to Mt. Myoken and committed suicide by the sword.</e>
<cmt>妙見山はMt. Myokenとしました。</cmt>
<e type="check" ver="1">Kawakami and thirteen roshi returned to Mt. Myoken and committed suicide by the sword.</e>
<cmt>修正なし</cmt>
</sen>
</par>
<par id="17">
<sen id="39">
<j>美玉三平と中島太郎兵衛は農民に襲撃され射殺された。</j>
<e type="trans" ver="1">Sanpei MITAMA and Tarobee NAKAJIMA were attacked by the farmers and shot to death.</e>
<cmt></cmt>
<e type="trans" ver="2">Sanpei MITAMA and Tarobee NAKAJIMA were attacked by the farmers and shot to death.</e>
<cmt>修正なし</cmt>
<e type="check" ver="1">Sanpei MITAMA and Tarobee NAKAJIMA were attacked by the farmers and shot to death.</e>
<cmt>修正なし</cmt>
</sen>
<sen id="40">
<j>平野は兵を解散させると鳥取へ向かったが捕らえられ、京の六角獄舎へ送られる。</j>
<e type="trans" ver="1">Hirano dissolved the army and headed to Tottori, but he was caught and sent to Rokkaku prison house in Kyoto.</e>
<cmt></cmt>
<e type="trans" ver="2">Hirano dissolved the army and headed to Tottori, but he was caught and sent to Rokkaku prison house in Kyoto.</e>
<cmt>修正なし</cmt>
<e type="check" ver="1">Hirano dissolved the army and headed to Tottori, but he was caught and sent to Rokkaku prison house in Kyoto.</e>
<cmt>修正なし</cmt>
</sen>
<sen id="41">
<j>その他の浪士たちも戦死、逃亡、捕縛された。</j>
<e type="trans" ver="1">The other roshi died, fled or were arrested.</e>
<cmt></cmt>
<e type="trans" ver="2">The other roshi died, fled or were arrested.</e>
<cmt>修正なし</cmt>
<e type="check" ver="1">The other roshi died, fled or were arrested.</e>
<cmt>修正なし</cmt>
</sen>
</par>
<par id="18">
<sen id="42">
<j>元治元年（1864年）7月の禁門の変の際に平野は幕吏によって六角獄舎で殺害された。</j>
<e type="trans" ver="1">In July 1864, Hirano was killed by a shogunate official in Rokkaku prison house, when the Hamaguri Rebellion (kinmon no hen) occurred.</e>
<cmt></cmt>
<e type="trans" ver="2">In July 1864, Hirano was killed by a shogunate official in Rokkaku prison house, when the Kimmon no Hen (Conspiracy of Kimmon) occurred.</e>
<cmt>禁門の変の訳を単語リストに揃えました。</cmt>
<e type="check" ver="1">In July 1864, Hirano was killed by a shogunate official in Rokkaku prison house, when the Kimmon no Hen (Conspiracy of Kimmon) occurred.</e>
<cmt>修正なし</cmt>
</sen>
</par>
<par id="19">
<sen id="43">
<j>北垣国道は生き残り、維新後に京都府知事となっている。</j>
<e type="trans" ver="1">Kunimichi KITAGAKI survived and became the governor of Kyoto Prefecture after the Meiji Restoration.</e>
<cmt></cmt>
<e type="trans" ver="2">Kunimichi KITAGAKI survived and became the governor of Kyoto Prefecture after the Meiji Restoration.</e>
<cmt>修正なし</cmt>
<e type="check" ver="1">Kunimichi KITAGAKI survived and became the governor of Kyoto Prefecture after the Meiji Restoration.</e>
<cmt>修正なし</cmt>
</sen>
</par>
<par id="20">
<sen id="44">
<j>生野での挙兵はあっけなく失敗したが、この挙兵は天誅組の挙兵とともに明治維新の導火線となったと評価されている。</j>
<e type="trans" ver="1">Raising an army quickly failed, but this army as well as the army of Tenchugumi, are appraised for being a trigger for the Meiji Restoration.</e>
<cmt></cmt>
<e type="trans" ver="2">Raising an army quickly failed, but this army as well as the army of Tenchugumi, are appraised for being a trigger for the Meiji Restoration.</e>
<cmt>修正なし</cmt>
<e type="check" ver="1">Raising an army quickly failed, but this army as well as the army of Tenchugumi, are appraised for being a trigger for the Meiji Restoration.</e>
<cmt>修正なし</cmt>
</sen>
</par>
<copyright>copyright (c) 2010 でここ(id:9565), Yakamaro(id:196844), Reggaeman(id:6214), ひろくん(id:79638), 味っ子(id:17086), Hukidera(id:87796), Maakun(id:16735), Ic ket(id:186941), 独立行政法人情報通信研究機構．このテキストの利用はCreative Commons Attribution-Share-Alike License 3.0 の条件の下に許諾されます．（この著作権者一覧には、Wikipedia IPユーザーを含んでおりません．この点に関するお問い合わせはこちらまで：kyoto-corpus@khn.nict.go.jp）</copyright>
</art>