<?xml version="1.0" encoding="UTF-8"?>
<art orl="ja" trl="en">
<inf yea="">jawiki-20090527-pages-articles.xml</inf>
<tit>
<j>一進会</j>
<e type="trans" ver="1">Isshinkai</e>
<cmt></cmt>
<e type="trans" ver="2">Isshinkai</e>
<cmt>修正なし</cmt>
<e type="check" ver="1">Isshinkai</e>
<cmt>修正なし</cmt>
</tit>
<par id="1">
<sen id="1">
<j>一進会（イルチンフェ・いっしんかい）とは、1904年から1910年まで大韓帝国で活動した当時最大の政治結社。</j>
<e type="trans" ver="1">Isshinkai was a biggest political association of the times which was active in the Korean Empire from 1904 to 1910.</e>
<cmt></cmt>
<e type="trans" ver="2">Isshinkai(イルチンフェ) was a biggest political association of the times which was active in the Korean Empire from 1904 to 1910.</e>
<cmt>イルチンフェの英語表記は不明のため、カタカナのまま追記しました。</cmt>
<e type="check" ver="1">Isshinkai(イルチンフェ) was a biggest political association of the times which was active in the Korean Empire from 1904 to 1910.</e>
<cmt>修正なし</cmt>
</sen>
<sen id="2">
<j>一般にチンイルパとみなされる。</j>
<e type="trans" ver="1">It is generally regarded as Pro-Japan.</e>
<cmt>「 チンイルパ」は韓国語で「親日家」という意味だそうです。</cmt>
<e type="trans" ver="2">It is generally regarded as Pro-Japan.</e>
<cmt>修正なし</cmt>
<e type="check" ver="1">It is generally regarded as Pro-Japan.</e>
<cmt>修正なし</cmt>
</sen>
</par>
<par id="2">
<sen id="3">
<j>宮廷での権力闘争に幻滅し、次第に外国勢力の力を借りてでも韓国の近代化を成し遂げようとする方向に傾いていきつつあった一部開化派の人々が設立した団体。</j>
<e type="trans" ver="1">It was an organization founded by a part of Kaika group which was tired of the struggle for power in the court and heading to the direction to accomplish the modernization of South Korea even if it needs foreign countries&apos; supports.</e>
<cmt></cmt>
<e type="trans" ver="2">It was an organization founded by a part of Kaika group which was tired of the struggle for power in the court and heading to the direction to accomplish the modernization of South Korea even if it needed foreign countries&apos; supports.</e>
<cmt>needs=&gt;needed(過去形）にしました。</cmt>
<e type="check" ver="1">It was an organization founded by a part of Kaika group which was tired of the struggle for power in the court and heading to the direction to accomplish the modernization of South Korea even if it needed foreign countries&apos; supports.</e>
<cmt>修正なし</cmt>
</sen>
<sen id="4">
<j>中でも日清戦争、日露戦争の勝利により世界的に影響力を強めつつあった大日本帝国に注目・接近し、日本政府・日本軍の特別の庇護を受けた。</j>
<e type="trans" ver="1">They especially put an eye and approached to Empire of Japan which was increasing the influencial power in the world after the victory of Sino-Japanese War and Russo-Japanese War, and they came under the patronage of Japanese Government and Japanese Army.</e>
<cmt></cmt>
<e type="trans" ver="2">They especially paid attention to and approached to Empire of Japan which was increasing the influencial power in the world after the victory of Sino-Japanese War and Russo-Japanese War, and they came under the patronage of Japanese Government and Japanese Army.</e>
<cmt>「注目」の表現を変更しました。</cmt>
<e type="check" ver="1">They especially paid attention to and approached to Empire of Japan which was increasing the influencial power in the world after the victory of Sino-Japanese War and Russo-Japanese War, and they came under the patronage of Japanese Government and Japanese Army.</e>
<cmt>修正なし</cmt>
</sen>
<sen id="5">
<j>日本と韓国の対等な連邦である韓日合邦（日韓併合とは異なる概念）の実現のために活発に活動した。</j>
<e type="trans" ver="1">They actively operated in order to realize Kan-Nichi Gappo, an consolidation of Japan and South Korea on an equal basis (a difference concept from the Japanese Annexation of Korea).</e>
<cmt></cmt>
<e type="trans" ver="2">They actively operated in order to realize Kan-Nichi Gappo, an consolidation of Japan and South Korea on an equal basis (a different concept from the Japanese Annexation of Korea).</e>
<cmt>difference=&gt;differentに修正しました。</cmt>
<e type="check" ver="1">They actively operated in order to realize Kan-Nichi Gappo, an consolidation of Japan and South Korea on an equal basis (a different concept from the Japanese Annexation of Korea).</e>
<cmt>修正なし</cmt>
</sen>
</par>
<par id="3">
<sen id="6">
<j>当時、大韓帝国では最も大きな政治結社であり、会員数は80万人から100万人であった。</j>
<e type="trans" ver="1">In the times, it was the biggest political association of South Korea, and the number of members was between 800 thousands and one million.</e>
<cmt></cmt>
<e type="trans" ver="2">At that time, it was the biggest political association of The Korean Empire, and the number of its members was between 800 thousands and one million.</e>
<cmt>「当時」の表現を変更しました。大韓帝国を登録の用語に修正しました。Itsを補いました。</cmt>
<e type="check" ver="1">At that time, it was the biggest political association of The Korean Empire, and the number of its members was between 800 thousands and one million.</e>
<cmt>修正なし</cmt>
</sen>
<sen id="7">
<j>韓日併合の目的を達成した一進会は、その後、韓国統監府が朝鮮内の政治的混乱を収拾するために朝鮮の政治結社を全面的に禁止したため、解散費用15万円を与えられ、他の政治結社と同様に解散したが、一進会を率いた宋秉畯らは朝鮮総督府中枢院顧問となり合併後の朝鮮の政治にも大きく影響を与え続けた。</j>
<e type="trans" ver="1">After Isshinkai accomplished the annexation between Korea and Japan, Kankoku Tokan-fu entirely forbade making any political association in Korea in order to suppress the political confusion in Korea, so they were compelled to dismiss as the other political associations did in exchange of 150 thousands yen given as dissolution allowance, but Song Byung-joon and others who had been leading Isshinkai assumed office as adviser of Chusuin (a government office in Korea) of Chosen Sotoku-fu and kept affecting on the korean politics after the annexation.</e>
<cmt></cmt>
<e type="trans" ver="2">After Isshinkai accomplished the annexation between Korea and Japan, Kankoku Tokan-fu (South Korea Protection Agency) entirely forbade making any political association in Korea in order to suppress the political confusion in Korea, so they were compelled to dismiss as the other political associations did in exchange of 150 thousand yen given as dissolution allowance, but Song Byung-joon and others who had been leading Isshinkai assumed office as adviser of Chusuin (a government office in Korea) of Chosen Sotoku-fu (Governor-General of Korea) and kept affecting on the Korean politics after the annexation.</e>
<cmt>韓国統監府/朝鮮総督府の説明を括弧で追記しました。Thousands yen =&gt; thousand yenに修正しました。括弧を追加しました。（Chusuinの説明の前）Koreanのkを大文字にしました。</cmt>
<e type="check" ver="1">After Isshinkai accomplished the annexation between Korea and Japan, Kankoku Tokan-fu (South Korea Protection Agency) entirely forbade making any political association in Korea in order to suppress the political confusion in Korea, so they were compelled to dismiss as the other political associations did in exchange of 150 thousand yen given as dissolution allowance, but Song Byung-joon and others who had been leading Isshinkai assumed office as adviser of Chusuin (a government office in Korea) of Chosen Sotoku-fu (Governor-General of Korea) and kept affecting on the Korean politics after the annexation.</e>
<cmt>修正なし</cmt>
</sen>
</par>
<par id="4">
<sen id="8">
<j>背景</j>
<e type="trans" ver="1">Background</e>
<cmt></cmt>
<e type="trans" ver="2">Background</e>
<cmt>修正なし</cmt>
<e type="check" ver="1">Background</e>
<cmt>修正なし</cmt>
</sen>
<sen id="9">
<j>朝鮮では、日清戦争で日本が清に勝利すると、王妃である閔妃が朝鮮で一層強化する日本の支配力を警戒した。</j>
<e type="trans" ver="1">In Korea after Japan defeated Shin in Sino-Japanese War, Empress Myeongseong took precautions against Japan which dominating power was further increasing in Korea.</e>
<cmt></cmt>
<e type="trans" ver="2">In Korea, after Japan defeated Shin in Sino-Japanese War, Empress Myeongseong took precautions against Japan of which dominating power was further increasing in Korea.</e>
<cmt>In Koreaのあとにカンマを入れました。Which =&gt; of whichにしました。</cmt>
<e type="check" ver="1">In Korea, after Japan defeated Shin in Sino-Japanese War, Empress Myeongseong took precautions against Japan of which dominating power was further increasing in Korea.</e>
<cmt>修正なし</cmt>
</sen>
<sen id="10">
<j>三国干渉によってロシア帝国の東アジアへの影響力が強まったことで、日本への牽制を含めて親露政策を強めるようになる。</j>
<e type="trans" ver="1">The Russian Empire enhanced its clout to East Asia after the Triple Intervention, so Korea enhanced the pro-Russia policy including feint to Japan.</e>
<cmt></cmt>
<e type="trans" ver="2">The Russian Empire enhanced its clout to East Asia after the Triple Intervention, so Korea enhanced the pro-Russia policy including feint to Japan.</e>
<cmt>修正なし</cmt>
<e type="check" ver="1">The Russian Empire enhanced its clout to East Asia after the Triple Intervention, so Korea enhanced the pro-Russia policy including feint to Japan.</e>
<cmt>修正なし</cmt>
</sen>
<sen id="11">
<j>その後、乙未事変で閔妃が暗殺された。（殺害現場にいた純宗の言で『乙未事件ニ際シ、現ニ朕ガ目撃セシ国母ノ仇、禹範善』となっているだけでなく、この禹範善は『禹ハ旧年王妃ヲ弑セシハ自己ナリトノ意ヲ漏セリ』と自ら犯人であることを漏らしている。(アジア歴史資料センター『在本邦韓国亡命者禹範善同国人高永根魯允明等ニ於テ殺害一件』)）</j>
<e type="trans" ver="1">After that, Empress Myeongseong was assassinated in Itsubi Incident (Sunjong who was at the crime scene said, &apos;I witnessed 禹範善 (우범선) killed our mother in Itsubi Incident.&apos;, and also 禹範善 (우범선) confessed to have killed Empress.) (&apos;A case of 禹範善 (우범선), a Korean refugee in Japan, murdered by 高永根 and 魯允明.&apos; Japan Center for Asian Historical Records</e>
<cmt>originalで、(アジア歴史資料センター『在本邦韓国亡命者禹範善同国人高永根魯允明等ニ於テ殺害一件』)）の部分が下のセルに入っていましたが、参考文献のようなので上のセルに入れました。  「高永根」と「魯允明」については日本語以外の表記が見つかりませんでした。</cmt>
<e type="trans" ver="2">After that, Empress Myeongseong was assassinated in Itsubi Incident (Sunjong who was at the crime scene said, &quot;I witnessed 禹範善 (우범선) killed our mother in Itsubi Incident&quot;, and also 禹範善 (우범선) confessed to have killed Empress.) (&apos;A case of 禹範善 (우범선), a Korean refugee in Japan, murdered by 高永根 and 魯允明.&apos; [Japan Center for Asian Historical Records])</e>
<cmt>引用符と括弧を修正しました。読みは不明です。</cmt>
<e type="check" ver="1">After that, Empress Myeongseong was assassinated in Itsubi Incident (Sunjong who was at the crime scene said, &quot;I witnessed Woo Beomseon) killed our mother in Itsubi Incident&quot;, and also Woo Beomseon confessed to have killed Empress.) (&apos;A case of Woo Beomseon), a Korean refugee in Japan, murdered by GO Yeong-Geun and 魯允明.&apos; [Japan Center for Asian Historical Records])</e>
<cmt>「魯允明」の読み不明</cmt>
</sen>
<sen id="12">
<j>1896年2月11日、親露派の李範晋や李完用らによってクーデターが行われ国王の高宗 (朝鮮王)がロシア在外公館に移り執務（露館播遷）を行うようになった。</j>
<e type="trans" ver="1">On February 11, 1896, pro-Russian 李範晋, 李完用 and others carried out a coup d&apos;état, so King Gao Zong (Korean King) transferred to a Russian government establishment to carry out his work (Rokanhasen).</e>
<cmt>「李範晋」と「李完用」については日本語以外の表記が見つかりませんでした。</cmt>
<e type="trans" ver="2">On February 11, 1896, pro-Russian 李範晋, Lee, Wan-yong and others carried out a coup d&apos;état, so King Gao Zong (Korean King) transferred to a Russian government establishment to carry out his work (Rokanhasen).</e>
<cmt>「李範晋」の表記はわかりません。「李完用」はわかったので表記を修正しました。</cmt>
<e type="check" ver="1">On February 11, 1896, pro-Russian Bum Chin Lee, Lee Wan-yong and others carried out a coup d&apos;etat, so King Gao Zong (Korean King) transferred to a Russian government establishment to carry out his work (Rokanhasen).</e>
<cmt>人名を英語表記</cmt>
</sen>
<sen id="13">
<j>日本の後押しを受けていた開化派政権は崩壊し、ロシアの影響力が強まった。</j>
<e type="trans" ver="1">Kaika group&apos;s government supported by Japan fell apart while Russia&apos;s influence increased.</e>
<cmt></cmt>
<e type="trans" ver="2">Kaika group&apos;s government supported by Japan fell apart while Russia&apos;s influence increased.</e>
<cmt>修正なし</cmt>
<e type="check" ver="1">Kaika group&apos;s government supported by Japan fell apart while Russia&apos;s influence increased.</e>
<cmt>修正なし</cmt>
</sen>
<sen id="14">
<j>1896年7月、開化派の流れを汲む人たちが朝鮮の自主独立、法治主義の確立、新教育の振興、農業の改良、工業の育成、愛国心、君主への忠誠心の培養を訴え李完用らが独立協会を設立した。</j>
<e type="trans" ver="1">In July 1896, the people following Kaika group called for the independence of Korea, establishment of legalism, promotion of new education, improvement of agriculture, encouragement of industry and raising of patriotism and loyalty to monarch, and Lee, Wan-yong and others founded the Independence Club.</e>
<cmt></cmt>
<e type="trans" ver="2">In July 1896, the people following Kaika group called for the independence of Korea, establishment of legalism, promotion of new education, improvement of agriculture, encouragement of industry and raising of patriotism and loyalty to monarch, and Lee, Wan-yong and others founded the Independence Club.</e>
<cmt>修正なし</cmt>
<e type="check" ver="1">In July 1896, the people following Kaika group called for the independence of Korea, establishment of legalism, promotion of new education, improvement of agriculture, encouragement of industry and raising of patriotism and loyalty to monarch, and Lee, Wan-yong and others founded the Independence Club.</e>
<cmt>修正なし</cmt>
</sen>
</par>
<par id="5">
<sen id="15">
<j>1897年以降、ロシアの侵略政策が露骨になると独立協会は反露闘争を展開、国王の高宗に王宮に戻ることを要請した。</j>
<e type="trans" ver="1">After 1897, as Russia&apos;s aggressive policy was getting obvious, the Independence Club carried out an anti-Russia fight and demanded King Gao Zong to come back to the royal palace.</e>
<cmt></cmt>
<e type="trans" ver="2">After 1897, as Russia&apos;s aggressive policy was getting obvious, the Independence Club carried out an anti-Russia fight and demanded King Gao Zong to come back to the royal palace.</e>
<cmt>修正なし</cmt>
<e type="check" ver="1">After 1897, as Russia&apos;s aggressive policy was getting obvious, the Independence Club carried out an anti-Russia fight and demanded King Gao Zong to come back to the royal palace.</e>
<cmt>修正なし</cmt>
</sen>
<sen id="16">
<j>高宗は王宮に戻り、大韓帝国の独立を宣言した。</j>
<e type="trans" ver="1">Gao Zong came back to the royal palace, and the Korean Empire declared independence.</e>
<cmt></cmt>
<e type="trans" ver="2">Gao Zong came back to the royal palace, and the Korean Empire declared independence.</e>
<cmt>修正なし</cmt>
<e type="check" ver="1">Gao Zong came back to the royal palace, and the Korean Empire declared independence.</e>
<cmt>修正なし</cmt>
</sen>
<sen id="17">
<j>これによりロシアの勢力は朝鮮から後退した。</j>
<e type="trans" ver="1">Due to this, the Russian power retreated from Korea.</e>
<cmt></cmt>
<e type="trans" ver="2">Due to this, the Russian power retreated from Korea.</e>
<cmt>修正なし</cmt>
<e type="check" ver="1">Due to this, the Russian power retreated from Korea.</e>
<cmt>修正なし</cmt>
</sen>
<sen id="18">
<j>しかし独立協会の主張は次第に守旧派官僚との対立を招き、最終的に高宗の勅令により独立協会は解散させられた。</j>
<e type="trans" ver="1">However, the Independence Club&apos;s insistence caused a confrontation with the bureaucracy of old-guard crony, and finally they were compelled to dismiss following the decree of Gao Zong.</e>
<cmt></cmt>
<e type="trans" ver="2">However, the Independence Club&apos;s insistence caused a confrontation with the bureaucracy of old-guard crony, and finally they were compelled to dismiss following the decree of Gao Zong.</e>
<cmt>修正なし</cmt>
<e type="check" ver="1">However, the Independence Club&apos;s insistence caused a confrontation with the bureaucracy of old-guard crony, and finally they were compelled to dismiss following the decree of Gao Zong.</e>
<cmt>修正なし</cmt>
</sen>
</par>
<par id="6">
<sen id="19">
<j>ロシアの勢力が朝鮮から後退したことによって再び日本の勢力が増大し韓国の経済的支配を進めた。</j>
<e type="trans" ver="1">Russia&apos;s retreat from Korea encouraged Japan to get back the power, and it promoted the economic domination in Korea.</e>
<cmt></cmt>
<e type="trans" ver="2">Russia&apos;s retreat from Korea encouraged Japan to get back the power, and it promoted the economic domination in Korea.</e>
<cmt>修正なし</cmt>
<e type="check" ver="1">Russia&apos;s retreat from Korea encouraged Japan to get back the power, and it promoted the economic domination in Korea.</e>
<cmt>修正なし</cmt>
</sen>
<sen id="20">
<j>ロシアと日本は朝鮮や満州の利権を巡り対立を深めた。</j>
<e type="trans" ver="1">Russia and Japan deepened their conflict for the interests of Korea and Manchuria.</e>
<cmt></cmt>
<e type="trans" ver="2">Russia and Japan deepened their conflict for the interests of Korea and Manchuria.</e>
<cmt>修正なし</cmt>
<e type="check" ver="1">Russia and Japan deepened their conflict for the interests of Korea and Manchuria.</e>
<cmt>修正なし</cmt>
</sen>
<sen id="21">
<j>こうした背景のもと、日露戦争中に日本軍通訳をつとめた宋秉畯が日本の影響下に政治改革のための組織を計画したが、この計画は元独立協会系の人々に受け入れられた。</j>
<e type="trans" ver="1">Due to this background, Song Byung-joon who had served as an interpreter for Japanese Army in Russo-Japanese War designed an organization for the political reform against the Japanese influence, and this plan was accepted by people following the independence club.</e>
<cmt></cmt>
<e type="trans" ver="2">Due to this background, Song Byung-joon who had served as an interpreter for Japanese Army in Russo-Japanese War designed an organization for the political reform against the Japanese influence, and this plan was accepted by people who had followed the independence club before.</e>
<cmt>「元銅区立協会系の」の部分の表現を変更しました。</cmt>
<e type="check" ver="1">Due to this background, Song Byung-joon who had served as an interpreter for Japanese Army in Russo-Japanese War designed an organization for the political reform against the Japanese influence, and this plan was accepted by people who had followed the independence club before.</e>
<cmt>修正なし</cmt>
</sen>
</par>
<par id="7">
<sen id="22">
<j>一進会の設立</j>
<e type="trans" ver="1">Foundation of Isshinkai</e>
<cmt></cmt>
<e type="trans" ver="2">Foundation of Isshinkai</e>
<cmt>修正なし</cmt>
<e type="check" ver="1">Foundation of Isshinkai</e>
<cmt>修正なし</cmt>
</sen>
<sen id="23">
<j>宋秉畯は、日露戦争のさなか、日韓議定書が締結された約半年後の1904年8月8日に独立協会系の尹始炳らと共に、一進会を設立する（当初、名称は「維新会」。</j>
<e type="trans" ver="1">Song Byung-joon founded Isshinkai along with 尹始炳 and others related to the independence club on August 8, 1904, about half a year after the conclusion of Japan-Korea Protocol in the middle of Russo-Japanese War (the initial name was &apos;Ishinkai&apos;).</e>
<cmt>「尹始炳」については日本語以外の表記が見つかりませんでした。</cmt>
<e type="trans" ver="2">Song Byung-joon founded Isshinkai along with 尹始炳 and others related to the independence club on August 8, 1904, about half a year after the conclusion of Japan-Korea Protocol in the middle of Russo-Japanese War (the initial name was &apos;Ishinkai&apos;).</e>
<cmt>修正なし</cmt>
<e type="check" ver="1">Song Byung-joon founded Isshinkai along with 尹始炳 and others related to the independence club on August 8, 1904, about half a year after the conclusion of Japan-Korea Protocol in the middle of Russo-Japanese War (the initial name was &apos;Ishinkai&apos;).</e>
<cmt>修正なし</cmt>
</sen>
<sen id="24">
<j>8月20日に「一進会」に改名）。</j>
<e type="trans" ver="1">On August 20, the name changed to &apos;Isshinkai&apos;.</e>
<cmt></cmt>
<e type="trans" ver="2">On August 20, the name was changed to &apos;Isshinkai&apos;.</e>
<cmt>受動態に変更しました。</cmt>
<e type="check" ver="1">On August 20, the name was changed to &apos;Isshinkai&apos;.</e>
<cmt>修正なし</cmt>
</sen>
<sen id="25">
<j>その後、もともと東学に参加していた宋秉畯は、東学の一部を引き継いだ進歩会を率いていた李容九と意見が合い、進歩会を吸収した。</j>
<e type="trans" ver="1">After that, Song Byung-joon who was originally a member of Donghak reached the consensus with 李容九 (이용구), a leader of Shinpokai following a part of Donghak, and merged Shinpokai.</e>
<cmt></cmt>
<e type="trans" ver="2">After that, Song Byung-joon who was originally a member of Donghak reached the consensus with 李容九 (이용구), a leader of Shinpokai following a part of Donghak, and merged Shinpokai.</e>
<cmt>修正なし</cmt>
<e type="check" ver="1">After that, Song Byung-joon who was originally a member of Donghak reached the consensus with 李容九 (이용구), a leader of Shinpokai following a part of Donghak, and merged Shinpokai.</e>
<cmt>修正なし</cmt>
</sen>
<sen id="26">
<j>ちなみに同年8月22日には第一次日韓協約が締結されている。</j>
<e type="trans" ver="1">For your information, the First Japan-Korea Treaty was concluded on August 22.</e>
<cmt></cmt>
<e type="trans" ver="2">For your information, the First Japan-Korea Treaty was concluded on August 22 of the same year.</e>
<cmt>同年を訳出しました。</cmt>
<e type="check" ver="1">For your information, the First Japan-Korea Treaty was concluded on August 22 of the same year.</e>
<cmt>修正なし</cmt>
</sen>
</par>
<par id="8">
<sen id="27">
<j>当初、尹始炳が会長であったが、尹始炳の要請によって李容九が会長に就任した。</j>
<e type="trans" ver="1">Initially, 尹始炳 was a chairman, but 李容九 (이용구) took over the office in response to 尹始炳&apos;s request.</e>
<cmt></cmt>
<e type="trans" ver="2">Initially, 尹始炳 was a chairman, but 李容九 (이용구) took over the office in response to 尹始炳&apos;s request.</e>
<cmt>修正なし</cmt>
<e type="check" ver="1">Initially, 尹始炳 was a chairman, but 李容九 (이용구) took over the office in response to 尹始炳&apos;s request.</e>
<cmt>修正なし</cmt>
</sen>
</par>
<par id="9">
<sen id="28">
<j>目的</j>
<e type="trans" ver="1">Purpose</e>
<cmt></cmt>
<e type="trans" ver="2">Purpose</e>
<cmt>修正なし</cmt>
<e type="check" ver="1">Purpose</e>
<cmt>修正なし</cmt>
</sen>
<sen id="29">
<j>一進会の掲げた目的は、独立協会に見られる民主主義、独立国家主義の思想を継承しており、「政治改革と民主の自由」を掲げている。</j>
<e type="trans" ver="1">The goal Isshinkai aimed at was &apos;political reform and people&apos;s freedom&apos; which succeeded to the thoughts of democracy and independent nationalism seen in the Independence Club.</e>
<cmt></cmt>
<e type="trans" ver="2">The goal Isshinkai aimed at was &apos;political reform and people&apos;s freedom&apos; which succeeded to the thoughts of democracy and independent nationalism seen in the Independence Club.</e>
<cmt>修正なし</cmt>
<e type="check" ver="1">The goal Isshinkai aimed at was &apos;political reform and people&apos;s freedom&apos; which succeeded to the thoughts of democracy and independent nationalism seen in the Independence Club.</e>
<cmt>修正なし</cmt>
</sen>
</par>
<par id="10">
<sen id="30">
<j>また一進会は、日露戦争時に設立され、日韓軍事同盟においてロシアを侵攻を阻止することが、ロシアの大韓帝国に対する影響力を弱め、さらには欧米列強のアジア進出を防ぎ、朝鮮の復興になると考えていた。</j>
<e type="trans" ver="1">Also, Isshinkai which was founded in the middle of Russo-Japanese War had a thought that blocking Russia&apos;s invasion under the Japan-Korea Military Alliance could weaken Russia&apos;s influence on the Korean Empire, that it further could prevent the allied western powers from advancing into Asia, and that it finally could lead to the restoration of Korea.</e>
<cmt></cmt>
<e type="trans" ver="2">Also, Isshinkai which was founded in the middle of Russo-Japanese War had a thought that blocking Russia&apos;s invasion under the Japan-Korea Military Alliance could weaken Russia&apos;s influence on the Korean Empire, that it further could prevent the allied western powers from advancing into Asia, and that it finally could lead to the restoration of Korea.</e>
<cmt>修正なし</cmt>
<e type="check" ver="1">Also, Isshinkai which was founded in the middle of Russo-Japanese War had a thought that blocking Russia&apos;s invasion under the Japan-Korea Military Alliance could weaken Russia&apos;s influence on the Korean Empire, that it further could prevent the allied western powers from advancing into Asia, and that it finally could lead to the restoration of Korea.</e>
<cmt>修正なし</cmt>
</sen>
</par>
<par id="11">
<sen id="31">
<j>活動</j>
<e type="trans" ver="1">Activities</e>
<cmt></cmt>
<e type="trans" ver="2">Activities</e>
<cmt>修正なし</cmt>
<e type="check" ver="1">Activities</e>
<cmt>修正なし</cmt>
</sen>
</par>
<sec id="1">
<tit>
<j>日露戦争における日本軍への協力</j>
<e type="trans" ver="1">Cooperation with Japanese Army in Russo-Japanese War</e>
<cmt></cmt>
<e type="trans" ver="2">Cooperation with Japanese Army in Russo-Japanese War</e>
<cmt>修正なし</cmt>
<e type="check" ver="1">Cooperation with Japanese Army in Russo-Japanese War</e>
<cmt>修正なし</cmt>
</tit>
<par id="1">
<sen id="32">
<j>一進会の設立当初、日本は一進会をそれほど評価してはいなかったが、一進会の設立後、宋秉畯は当時の日本の大佐、松石安治に対し書簡を送り、現状の高宗およびその官僚主導では大韓帝国の独立・維持は困難であると説明し、また京義線敷設の協力をも申し出ている。</j>
<e type="trans" ver="1">Japan initially wasn&apos;t putting a high estimation in Isshinkai, but after it was founded, Song Byung-joon sent a letter to Yasuharu MATSUISHI, a Japanese Colonel of the times, to explain that current regime led by Gao Zong and the bureaucracy couldn&apos;t bring independence and maintenance to Korean Empire, and he also offered a cooperation for the construction of Keigi Railroad.</e>
<cmt></cmt>
<e type="trans" ver="2">Japan initially wasn&apos;t putting a high estimation in Isshinkai, but after it was founded, Song Byung-joon sent a letter to Yasuharu MATSUISHI, a Japanese Colonel of the times, to explain that current regime led by Gao Zong and the bureaucracy couldn&apos;t bring independence and maintenance to Korean Empire, and he also offered a cooperation for the construction of Keigi Railroad.</e>
<cmt>修正なし</cmt>
<e type="check" ver="1">Japan initially wasn&apos;t putting a high estimation in Isshinkai, but after it was founded, Song Byung-joon sent a letter to Yasuharu MATSUISHI, a Japanese Colonel of the times, to explain that current regime led by Gao Zong and the bureaucracy couldn&apos;t bring independence and maintenance to Korean Empire, and he also offered a cooperation for the construction of Keigi Railroad.</e>
<cmt>修正なし</cmt>
</sen>
<sen id="33">
<j>当時の日露戦争においては、日本軍が物資輸送のため京義線の敷設を計画するが、日本軍の人員不足で計画が暗礁に乗り上げており、この際、一進会がこの敷設工事に無償支援し、会員14万人以上を動員した。</j>
<e type="trans" ver="1">In the Russo-Japanese War, Japanese Army planned to construct Keigi Railroad for transport of goods, but the plan was suspended due to the shortage of labors, so Isshinkai mobilized over 140 thousands members as free support for the construction of the railroad.</e>
<cmt></cmt>
<e type="trans" ver="2">In the Russo-Japanese War, Japanese Army planned to construct Keigi Railroad for transport of goods, but the plan was suspended due to the shortage of labors, so Isshinkai mobilized over 140 thousands members as free support for the construction of the railroad.</e>
<cmt>修正なし</cmt>
<e type="check" ver="1">In the Russo-Japanese War, Japanese Army planned to construct Keigi Railroad for transport of goods, but the plan was suspended due to the shortage of labors, so Isshinkai mobilized over 140 thousands members as free support for the construction of the railroad.</e>
<cmt>修正なし</cmt>
</sen>
<sen id="34">
<j>さらに一進会は、日本軍の軍事物資輸送も支援に乗り出し、10万人以上の会員が自費で日本軍の武器、食料を戦地まで運んでいる。</j>
<e type="trans" ver="1">Furthermore, Isshinkai began to support the transport of military goods for Japanese Army, and over 10 thousands members transported weapons and foods for Japanese Army at their own expense.</e>
<cmt></cmt>
<e type="trans" ver="2">Furthermore, Isshinkai began to support the transport of military goods for Japanese Army, and over 10 thousands members transported weapons and foods for Japanese Army at their own expense.</e>
<cmt>修正なし</cmt>
<e type="check" ver="1">Furthermore, Isshinkai began to support the transport of military goods for Japanese Army, and over 10 thousands members transported weapons and foods for Japanese Army at their own expense.</e>
<cmt>修正なし</cmt>
</sen>
<sen id="35">
<j>また、この日露戦争当時、一進会会員は、当時の伝統であった長髪、髷をやめ、自主独立運動の象徴としている。</j>
<e type="trans" ver="1">Also, during the Russo-Japanese War, the members of Isshinkai quit their long hair and beard which was a tradition of the times, as a symbol of the independent movement.</e>
<cmt></cmt>
<e type="trans" ver="2">Also, during the Russo-Japanese War, the members of Isshinkai quit their long hair and beard which was a tradition of the times, as a symbol of the independent movement.</e>
<cmt>修正なし</cmt>
<e type="check" ver="1">Also, during the Russo-Japanese War, the members of Isshinkai quit their long hair and beard which was a tradition of the times, as a symbol of the independent movement.</e>
<cmt>修正なし</cmt>
</sen>
<sen id="36">
<j>朝鮮では露館播遷で断髪令を廃止しており、このような断髪は一般市民からは考えられないものであった。</j>
<e type="trans" ver="1">In Korea, the order of bobbed hair had been abolished at the time of Rokanhasen, so such brobbed hair was unthinkable for general public.</e>
<cmt></cmt>
<e type="trans" ver="2">In Korea, the order of bobbed hair had been abolished at the time of Rokanhasen, so such brobbed hair was unthinkable for general public.</e>
<cmt>修正なし</cmt>
<e type="check" ver="1">In Korea, the order of bobbed hair had been abolished at the time of Rokanhasen, so such brobbed hair was unthinkable for general public.</e>
<cmt>修正なし</cmt>
</sen>
</par>
</sec>
<sec id="2">
<tit>
<j>統監政治</j>
<e type="trans" ver="1">Government by Inspector General</e>
<cmt></cmt>
<e type="trans" ver="2">Government by Inspector General</e>
<cmt>修正なし</cmt>
<e type="check" ver="1">Government by Inspector General</e>
<cmt>修正なし</cmt>
</tit>
<par id="1">
<sen id="37">
<j>1905年10月、日本政府は韓国保護権の確立の方針を閣議決定し、翌11月には伊藤博文を特使として派遣し、11月28日に第二次日韓協約の締結が強行された。</j>
<e type="trans" ver="1">In October 1905, Japanese Government made a cabinet decision on the policy to build the protection right for Korea, and in November, Hirobumi ITO was sent as a special envoy, and on November 28, the Eulsa Treaty was forced to be concluded.</e>
<cmt></cmt>
<e type="trans" ver="2">In October 1905, Japanese Government made a cabinet decision on the policy to build the protection right for Korea, and in November, Hirobumi ITO was sent as a special envoy, and on November 28, the Eulsa Treaty was forced to be concluded.</e>
<cmt>修正なし</cmt>
<e type="check" ver="1">In October 1905, Japanese Government made a cabinet decision on the policy to build the protection right for Korea, and in November, Hirobumi ITO was sent as a special envoy, and on November 28, the Eulsa Treaty was forced to be concluded.</e>
<cmt>修正なし</cmt>
</sen>
<sen id="38">
<j>これに先立ち、一進会は1905年11月5日に「外交権を日本政府に委任し日本の指導保護を受け、朝鮮の独立、安定を維持せよ」という宣言書を発表している。</j>
<e type="trans" ver="1">On November 5, 1905 before that, Isshinkai had announced their declaration that they transferred their diplomatic right to Japanese Government to go under the Japanese instruction and protection, for the purpose of maintaining Korea&apos;s independence and stability.</e>
<cmt></cmt>
<e type="trans" ver="2">On November 5, 1905 before that, Isshinkai had announced their declaration that they transferred their diplomatic right to Japanese Government to go under the Japanese instruction and protection, for the purpose of maintaining Korea&apos;s independence and stability.</e>
<cmt>修正なし</cmt>
<e type="check" ver="1">On November 5, 1905 before that, Isshinkai had announced their declaration that they transferred their diplomatic right to Japanese Government to go under the Japanese instruction and protection, for the purpose of maintaining Korea&apos;s independence and stability.</e>
<cmt>修正なし</cmt>
</sen>
</par>
<par id="2">
<sen id="39">
<j>韓国統治の総責任者伊藤博文は当初早期の韓国併合を反対していた。</j>
<e type="trans" ver="1">Hirobumi ITO, the person in charge of governing South Korea, was initially against carrying out the annexation of Korea in the early stage.</e>
<cmt></cmt>
<e type="trans" ver="2">Hirobumi ITO, the person in charge of governing South Korea, was initially against carrying out the annexation of Korea in the early stage.</e>
<cmt>修正なし</cmt>
<e type="check" ver="1">Hirobumi ITO, the person in charge of governing South Korea, was initially against carrying out the annexation of Korea in the early stage.</e>
<cmt>修正なし</cmt>
</sen>
</par>
<par id="3">
<sen id="40">
<j>しかし1909年10月、伊藤博文は満州のハルビン（哈爾浜）にて安重根によって暗殺され、短い中継ぎを挟み寺内正毅が第三代韓国統監（就任は1910年5月）となり、義兵戦争への弾圧を継続しつつ韓国併合への準備を進めていった。</j>
<e type="trans" ver="1">However, in October 1909, Hirobumi ITO was assassinated by An Jung-geun in Harbin of Manchuria, so after a short provisional term, Masatake TERAUCHI assumed office as the 3rd Inspector General of Korea (as of May 1910) and proceeded the preparation for the annexation of Korea, keeping oppression to Gihei War.</e>
<cmt></cmt>
<e type="trans" ver="2">However, in October 1909, Hirobumi ITO was assassinated by An Jung-geun in Harbin of Manchuria, so after a short provisional term, Masatake TERAUCHI assumed office as the 3rd Inspector General of Korea (as of May 1910) and proceeded the preparation for the annexation of Korea, keeping oppression to Gihei War.</e>
<cmt>修正なし</cmt>
<e type="check" ver="1">However, in October 1909, Hirobumi ITO was assassinated by An Jung-geun in Harbin of Manchuria, so after a short provisional term, Masatake TERAUCHI assumed office as the 3rd Inspector General of Korea (as of May 1910) and proceeded the preparation for the annexation of Korea, keeping oppression to Gihei War.</e>
<cmt>修正なし</cmt>
</sen>
</par>
</sec>
<sec id="3">
<tit>
<j>韓日合邦の要請</j>
<e type="trans" ver="1">Request of the consolidation of Korea and Japan</e>
<cmt></cmt>
<e type="trans" ver="2">Request of the consolidation of Korea and Japan</e>
<cmt>修正なし</cmt>
<e type="check" ver="1">Request of the consolidation of Korea and Japan</e>
<cmt>修正なし</cmt>
</tit>
<par id="1">
<sen id="41">
<j>一進会は、1909年12月「韓日合邦を要求する声明書」を純宗 (朝鮮王)、第二代韓国統監曾禰荒助、首相李完用に送り、韓日合邦を要請している。</j>
<e type="trans" ver="1">In December 1909, Isshinkai sent the &apos;Statement to request the consolidation of Korea and Japan&apos; to Sunjong (Korean King), Sone ARASUKE, the 2nd Inspector General of Korea, and Prime Minister Lee, Wan-yong to request the consolidation of Korea and Japan.</e>
<cmt></cmt>
<e type="trans" ver="2">In December 1909, Isshinkai sent the &apos;Statement to request the consolidation of Korea and Japan&apos; to Sunjong (Korean King), Sone ARASUKE, the 2nd Inspector General of Korea, and Prime Minister Lee, Wan-yong to request the consolidation of Korea and Japan.</e>
<cmt>修正なし</cmt>
<e type="check" ver="1">In December 1909, Isshinkai sent the &apos;Statement to request the consolidation of Korea and Japan&apos; to Sunjong (Korean King), Sone ARASUKE, the 2nd Inspector General of Korea, and Prime Minister Lee, Wan-yong to request the consolidation of Korea and Japan.</e>
<cmt>修正なし</cmt>
</sen>
</par>
<par id="2">
<sen id="42">
<j>この建議書の中で、李容九は会員100万人の声明と称して、「日本は日清戦争で莫大な費用と多数の人命を費やし韓国を独立させてくれた。</j>
<e type="trans" ver="1">In this proposal, 李容九 (이용구) claimed as the statement of one million members as follows : Japan has dedicated an enormous expense and people&apos;s lives in Sino-Japanese War in order to bring independence to Korea.</e>
<cmt></cmt>
<e type="trans" ver="2">In this proposal, 李容九 (이용구) claimed as the statement of one million members as follows : Japan has dedicated an enormous expense and people&apos;s lives in Sino-Japanese War in order to bring independence to Korea.</e>
<cmt>修正なし</cmt>
<e type="check" ver="1">In this proposal, 李容九 (이용구) claimed as the statement of one million members as follows : Japan has dedicated an enormous expense and people&apos;s lives in Sino-Japanese War in order to bring independence to Korea.</e>
<cmt>修正なし</cmt>
</sen>
<sen id="43">
<j>また日露戦争では日本の損害は甲午の二十倍を出しながらも、韓国がロシアの口に飲み込まれる肉になるのを助け、東洋全体の平和を維持した。</j>
<e type="trans" ver="1">Besides, although Japan&apos;s loss in Russo-Japanese War was twenty times the Donghak Peasant Revolution, they helped Korea not to be swallowed into Russia&apos;s mouth and maintained the piece of entire Asia.</e>
<cmt>「甲午」は「甲午農民戦争」のことだと思われるので、そちらの方で英訳しています。</cmt>
<e type="trans" ver="2">Besides, although Japan&apos;s loss in Russo-Japanese War was twenty times as much as that of the Donghak Peasant Revolution, they helped Korea not to be swallowed into Russia&apos;s mouth and maintained the piece of entire Asia.</e>
<cmt>「の二十倍」の表現を修正しました。</cmt>
<e type="check" ver="1">Besides, although Japan&apos;s loss in Russo-Japanese War was twenty times as much as that of the Donghak Peasant Revolution, they helped Korea not to be swallowed into Russia&apos;s mouth and maintained the piece of entire Asia.</e>
<cmt>修正なし</cmt>
</sen>
<sen id="44">
<j>韓国はこれに感謝もせず、あちこちの国にすがり、外交権が奪われ、保護条約に至ったのは、我々が招いたのである。</j>
<e type="trans" ver="1">Nevertheless, Korea didn&apos;t appreciate it and begged every country, so it was our fault that our diplomatic right has been taken away and the protection treaty was concluded.</e>
<cmt></cmt>
<e type="trans" ver="2">Nevertheless, Korea didn&apos;t appreciate it and begged different countries, so it was our fault that our diplomatic right has been taken away and the protection treaty was concluded.</e>
<cmt>「あちこちの国」の表現を修正しました。</cmt>
<e type="check" ver="1">Nevertheless, Korea didn&apos;t appreciate it and begged different countries, so it was our fault that our diplomatic right has been taken away and the protection treaty was concluded.</e>
<cmt>修正なし</cmt>
</sen>
<sen id="45">
<j>第三次日韓協約、ハーグ密使事件も我々が招いたのである。</j>
<e type="trans" ver="1">The Japan-Korea Annexation Treaty and Hague Secret Emissary Affair were also due to our fault.</e>
<cmt></cmt>
<e type="trans" ver="2">The Japan-Korea Annexation Treaty and Hague Secret Emissary Affair were also due to our fault.</e>
<cmt>修正なし</cmt>
<e type="check" ver="1">The Japan-Korea Annexation Treaty and Hague Secret Emissary Affair were also due to our fault.</e>
<cmt>修正なし</cmt>
</sen>
<sen id="46">
<j>今後どのような危険が訪れるかも分からないが、これも我々が招いたことである。</j>
<e type="trans" ver="1">We don&apos;t know what danger is coming up next, but it is also our fault.</e>
<cmt></cmt>
<e type="trans" ver="2">We don&apos;t know what danger is coming up next, but it is also our fault.</e>
<cmt>修正なし</cmt>
<e type="check" ver="1">We don&apos;t know what danger is coming up next, but it is also our fault.</e>
<cmt>修正なし</cmt>
</sen>
<sen id="47">
<j>我が国の皇帝陛下と日本明治天皇に懇願し、我々も一等国民の待遇を享受して、政府と社会を発展させようではないか」と主張した。</j>
<e type="trans" ver="1">We should beg His Imperial Majesty and Meiji Emperor of Japan in order to be able to receive the treatment as Itto Kokumin (First-class people) to develop our government and society.</e>
<cmt>一原文一訳文の例外対処</cmt>
<e type="trans" ver="2">We should beg his Imperial Majesty and Meiji Emperor of Japan in order to be able to receive the treatment as Itto Kokumin (First-class people) to develop our government and society.</e>
<cmt>His=&gt;hisに修正しました。</cmt>
<e type="check" ver="1">We should beg his Imperial Majesty and Meiji Emperor of Japan in order to be able to receive the treatment as Itto Kokumin (First-class people) to develop our government and society.</e>
<cmt>修正なし</cmt>
</sen>
<sen id="48">
<j>韓国と日本の連邦形式の対等合邦を求めた。</j>
<e type="trans" ver="1">Thus, he called for the equal consolidation of Korea and Japan which would take a form of federation.</e>
<cmt>一原文一訳文の例外対処</cmt>
<e type="trans" ver="2">Thus, he called for the equal consolidation of Korea and Japan which would take a form of federation.</e>
<cmt>修正なし</cmt>
<e type="check" ver="1">Thus, he called for the equal consolidation of Korea and Japan which would take a form of federation.</e>
<cmt>修正なし</cmt>
</sen>
</par>
</sec>
<sec id="4">
<tit>
<j>解散</j>
<e type="trans" ver="1">Dismissal</e>
<cmt></cmt>
<e type="trans" ver="2">Dismissal</e>
<cmt>修正なし</cmt>
<e type="check" ver="1">Dismissal</e>
<cmt>修正なし</cmt>
</tit>
<par id="1">
<sen id="49">
<j>一進会の主張はあくまで日韓両国民の対等な地位に基づく日韓共栄であって日本の考える韓国の吸収併合とは全く異なるものであることや、日韓併合については韓国側の要求は一切受け入れない方針であったため日本政府は一進会の請願を拒否した。</j>
<e type="trans" ver="1">The Japanese Government refused their demand because Isshinkai claimed for the mutual prosperity between Korea and Japan on a basis of Korean and Japanese people&apos;s equal position, which was completely different from the merger and annexation of Korea Japan was expecting, and also Japan was taking its own policy that any request from Korea was unacceptable for the Japanese annexation of Korea.</e>
<cmt></cmt>
<e type="trans" ver="2">The Japanese Government refused their demand because Isshinkai claimed for the mutual prosperity between Korea and Japan on a basis of Korean and Japanese people&apos;s equal position, which was completely different from the merger and annexation of Korea, that Japan was expecting, and also Japan was taking its own policy that any request from Korea was unacceptable for the Japanese annexation of Korea.</e>
<cmt>Japan was expectingの前にthatを入れました。</cmt>
<e type="check" ver="1">The Japanese Government refused their demand because Isshinkai claimed for the mutual prosperity between Korea and Japan on a basis of Korean and Japanese people&apos;s equal position, which was completely different from the merger and annexation of Korea, that Japan was expecting, and also Japan was taking its own policy that any request from Korea was unacceptable for the Japanese annexation of Korea.</e>
<cmt>修正なし</cmt>
</sen>
<sen id="50">
<j>これは、当時の大韓帝国の巨額の債務や土地インフラに膨大な予算が必要になることから日本国民の理解を得ることは難しいとの政治判断からであった。</j>
<e type="trans" ver="1">It was a political decision from the judgement that it would be difficult to have Japanese people&apos;s understanding, because, at the time, the Korean Empire held an enormous debt and also needed a lot of budget for the land infrastructure.</e>
<cmt></cmt>
<e type="trans" ver="2">It was a political decision from the judgement that it would be difficult to have Japanese people&apos;s understanding, because, at the time, the Korean Empire held an enormous debt and also needed a lot of budget for the land infrastructure.</e>
<cmt>修正なし</cmt>
<e type="check" ver="1">It was a political decision from the judgement that it would be difficult to have Japanese people&apos;s understanding, because, at the time, the Korean Empire held an enormous debt and also needed a lot of budget for the land infrastructure.</e>
<cmt>修正なし</cmt>
</sen>
<sen id="51">
<j>一方、一進会の宋秉畯も、韓日の対等合邦は国力の差から困難であると判断して韓日併合論を展開し、1910年、桂内閣により韓日併合がなされた。</j>
<e type="trans" ver="1">On the other hand, Song Byung-joon of Isshinkai was convinced that the equal consolidation of Korea and Japan would be difficult if considering the difference of the two countries&apos; national power, so he next rolled out the theory as to Japan&apos;s annexation of Korea which was finally concluded by Katsura Cabinet in 1910.</e>
<cmt></cmt>
<e type="trans" ver="2">On the other hand, Song Byung-joon of Isshinkai was convinced that the equal consolidation of Korea and Japan would be difficult if considering the difference of the two countries&apos; national power, so he next rolled out the theory as to Japan&apos;s annexation of Korea which was finally concluded by Katsura Cabinet in 1910.</e>
<cmt>修正なし</cmt>
<e type="check" ver="1">On the other hand, Song Byung-joon of Isshinkai was convinced that the equal consolidation of Korea and Japan would be difficult if considering the difference of the two countries&apos; national power, so he next rolled out the theory as to Japan&apos;s annexation of Korea which was finally concluded by Katsura Cabinet in 1910.</e>
<cmt>修正なし</cmt>
</sen>
<sen id="52">
<j>日韓併合後、韓国統監府は、親日派／非親日派の政治団体の対立による治安の混乱を収拾するため、朝鮮の全ての政治結社を禁止し解散させた。</j>
<e type="trans" ver="1">After Japan&apos;s annexation of Korea, the Kankoku Sokan-fu forbade and dismissed all political associations of Korea in order to suppress the confusion and regain the public safety caused by the confliction between pro-Japanese and anti-Japanese political associations.</e>
<cmt></cmt>
<e type="trans" ver="2">After Japan&apos;s annexation of Korea, the Kankoku Sokan-fu forbade and dismissed all political associations of Korea in order to suppress the confusion and regain the public safety caused by the confliction between pro-Japanese and anti-Japanese political associations.</e>
<cmt>修正なし</cmt>
<e type="check" ver="1">After Japan&apos;s annexation of Korea, the Kankoku Sokan-fu forbade and dismissed all political associations of Korea in order to suppress the confusion and regain the public safety caused by the confliction between pro-Japanese and anti-Japanese political associations.</e>
<cmt>修正なし</cmt>
</sen>
<sen id="53">
<j>これにより、一進会は併合直後の1910年9月12日に日本政府によって解散を命じられ、解散費用15万円を与えられ、同年9月25日に解散した。</j>
<e type="trans" ver="1">Due to this, Isshinkai was ordered to dismiss by Japanese Government on Spetember 12, 1910 just after the annexation, and with 150 thousands yen given as a dissolution allowance, it dismissed on September 25 of the same year.</e>
<cmt></cmt>
<e type="trans" ver="2">Due to this, Isshinkai was ordered to dismiss by Japanese Government on September 12, 1910 just after the annexation, and with 150 thousand yen given as a dissolution allowance, it dismissed on September 25 of the same year.</e>
<cmt>Septemeberのスペルミスを修正しました。Thousands=&gt;thousandに修正しました。</cmt>
<e type="check" ver="1">Due to this, Isshinkai was ordered to dismiss by Japanese Government on September 12, 1910 just after the annexation, and with 150 thousand yen given as a dissolution allowance, it dismissed on September 25 of the same year.</e>
<cmt>修正なし</cmt>
</sen>
<sen id="54">
<j>一進会を率い、韓日併合論を説いた宋秉畯らは朝鮮総督府中枢院顧問となり、合併後の朝鮮の政治にも大きく影響を与え続け、その後、その功績により宋秉畯には伯爵位が与えられた。</j>
<e type="trans" ver="1">Song Byung-joon and others who led Isshinkai and supported the theory as to Japan&apos;s annexation of Korea assumed office as adviser of Chusuin (a government office in Korea) of Chosen Sotoku-fu and kept affecting on the korean politics after the annexation, and later Song Byung-joon was given a title of count for his achievement.</e>
<cmt></cmt>
<e type="trans" ver="2">Song Byung-joon and others who led Isshinkai and supported the theory as to Japan&apos;s annexation of Korea assumed office as adviser of Chusuin (a government office in Korea) of Chosen Sotoku-fu and kept affecting on the Korean politics after the annexation, and later Song Byung-joon was given a title of count for his achievement.</e>
<cmt>Korean politics(Kを大文字）に修正しました。</cmt>
<e type="check" ver="1">Song Byung-joon and others who led Isshinkai and supported the theory as to Japan&apos;s annexation of Korea assumed office as adviser of Chusuin (a government office in Korea) of Chosen Sotoku-fu and kept affecting on the Korean politics after the annexation, and later Song Byung-joon was given a title of count for his achievement.</e>
<cmt>修正なし</cmt>
</sen>
</par>
<par id="2">
<sen id="55">
<j>評価</j>
<e type="trans" ver="1">Public estimation</e>
<cmt></cmt>
<e type="trans" ver="2">Public estimation</e>
<cmt>修正なし</cmt>
<e type="check" ver="1">Public estimation</e>
<cmt>修正なし</cmt>
</sen>
<sen id="56">
<j>一進会に対する評価はその活動の解釈や政治的立場によって大きく異る。</j>
<e type="trans" ver="1">The public estimation to Isshinkai varies depending on the understanding of his activities or the political position.</e>
<cmt></cmt>
<e type="trans" ver="2">The public estimation to Isshinkai has varied depending on the understanding of its activities or the political position.</e>
<cmt>varyの部分は完了形に修正しました。His=&gt;itsに修正しました。</cmt>
<e type="check" ver="1">The public estimation to Isshinkai has varied depending on the understanding of its activities or the political position.</e>
<cmt>修正なし</cmt>
</sen>
<sen id="57">
<j>以下には日韓において出版されている一般書籍での評価について概述する。</j>
<e type="trans" ver="1">The public estimation shown in the general books published in Japan or Korea are as follows.</e>
<cmt></cmt>
<e type="trans" ver="2">The public estimation shown in the general books published in Japan or Korea are as follows.</e>
<cmt>修正なし</cmt>
<e type="check" ver="1">The public estimation shown in the general books published in Japan or Korea are as follows.</e>
<cmt>修正なし</cmt>
</sen>
<sen id="58">
<j>（順不同）</j>
<e type="trans" ver="1">(in random order)</e>
<cmt></cmt>
<e type="trans" ver="2">(in random order)</e>
<cmt>修正なし</cmt>
<e type="check" ver="1">(in random order)</e>
<cmt>修正なし</cmt>
</sen>
</par>
<par id="3">
<sen id="59">
<j>平凡社の『朝鮮を知る事典』では、一進会を「親日御用団体」と呼び、表立った運動以外にスパイ活動などにも協力したとしている。</j>
<e type="trans" ver="1">In &quot;朝鮮を知る事典&quot;(Encyclopedia to know Korea) published by Heibon-sya, Isshinkai is called &apos;pro-Japanese order-taker organization&apos; with the mention that they cooperated as spy other than their outer activities.</e>
<cmt></cmt>
<e type="trans" ver="2">In &quot;朝鮮を知る事典&quot;(Encyclopedia to know Korea) published by Heibon-sya, Isshinkai is called &apos;pro-Japanese order-taker organization&apos; with the mention that they cooperated as spy other than their outer activities.</e>
<cmt>修正なし</cmt>
<e type="check" ver="1">In &quot;朝鮮を知る事典&quot;(Encyclopedia to know Korea) published by Heibon-sya, Isshinkai is called &apos;pro-Japanese order-taker organization&apos; with the mention that they cooperated as spy other than their outer activities.</e>
<cmt>修正なし</cmt>
</sen>
<sen id="60">
<j>また、親日団体としての働きについてはプラスの効果よりも民衆の反発を招いたマイナスの結果の部分が大きかったとしている。</j>
<e type="trans" ver="1">It also mentions that their job as pro-Japanese organizaiton provoked people&apos;s antipahty, so the negative result was much bigger than the positive effect.</e>
<cmt></cmt>
<e type="trans" ver="2">It also mentions that their job as pro-Japanese organizaiton provoked people&apos;s antipathy, so the negative result was much bigger than the positive effect.</e>
<cmt>antipathyのスペルミスを修正しました。</cmt>
<e type="check" ver="1">It also mentions that their job as pro-Japanese organizaiton provoked people&apos;s antipathy, so the negative result was much bigger than the positive effect.</e>
<cmt>修正なし</cmt>
</sen>
<sen id="61">
<j>また、一進会の実態が「李容九や宋秉畯などの利権集団」であったとも記述している。</j>
<e type="trans" ver="1">Besides, it mentions that the real Isshinkai was &apos;an organization seeking for the interests of 李容九 (이용구) or Song Byung-joon&apos;.</e>
<cmt></cmt>
<e type="trans" ver="2">Besides, it mentions that the real Isshinkai was &apos;an organization seeking for the interests of 李容九 (이용구), Song Byung-joon or others&apos;.</e>
<cmt>or othersを追加しました。</cmt>
<e type="check" ver="1">Besides, it mentions that the real Isshinkai was &apos;an organization seeking for the interests of Lee Yong-gu, Song Byung-joon or others&apos;.</e>
<cmt>人名を英語表記</cmt>
</sen>
</par>
<par id="4">
<sen id="62">
<j>三省堂の『朝鮮の歴史　新版』では、一進会が1909年に出した声明について、民衆の声を代表しておらず、かつ「会員100万人」も実体のない数字だったとしている。</j>
<e type="trans" ver="1">In &apos;History of Korea, New Edition&apos; published by Sanseido, there is an mention that the statement issued by Isshinkai in 1909 was not representing people&apos;s voice, and that the number described as &apos;one million members&apos; was unsubstantial.</e>
<cmt></cmt>
<e type="trans" ver="2">In &apos;History of Korea, New Edition&apos; published by Sanseido, there is an mention that the statement issued by Isshinkai in 1909 was not representing people&apos;s voice, and that the number described as &apos;one million members&apos; was unsubstantial.</e>
<cmt>修正なし</cmt>
<e type="check" ver="1">In &apos;History of Korea, New Edition&apos; published by Sanseido, there is an mention that the statement issued by Isshinkai in 1909 was not representing people&apos;s voice, and that the number described as &apos;one million members&apos; was unsubstantial.</e>
<cmt>修正なし</cmt>
</sen>
</par>
<par id="5">
<sen id="63">
<j>金完燮の『親日派のための弁明』（2002）では、一進会の運動を、李氏朝鮮政府の圧政をはねのけようとする農民階級（東学党→進歩会）と、支配階級出身で朝鮮の近代化をめざす改革派知識人グループ（維新会）、そして朝鮮近代化を支援することで「攻撃的な防御」を確保しようとする日本、の3つの改革勢力が結集されたものとして高く評価している。</j>
<e type="trans" ver="1">In &apos;Explanation for the sake of pro-Japan&apos; by 金完燮 (김완섭) (2002), the author highly evaluated the Isshinkai&apos;s movement, comparing their movment with a concentration of three revolutionary powers consisted of peasants who tried to reject the oppression of Joseon Dynasty Government (Togaku-to =&gt; Shinpo-kai), the group consisted of revolutionary intellectuals from governing class aimed at modernization of Korea (Ishin-kai) and Japan which tried to secure the &apos;aggressive protection&apos; by supporting the modernization of Korea.</e>
<cmt></cmt>
<e type="trans" ver="2">In &apos;Explanation for the sake of pro-Japan&apos; by 金完燮 (김완섭) (2002), the author highly evaluated the Isshinkai&apos;s movement, comparing their movment with a concentration of three revolutionary powers consisted of peasants who tried to reject the oppression of Joseon Dynasty Government (Togaku-to =&gt; Shinpo-kai), the group consisted of revolutionary intellectuals from governing class aimed at modernization of Korea (Ishin-kai) and Japan which tried to secure the &apos;aggressive protection&apos; by supporting the modernization of Korea.</e>
<cmt>→を半角記号に修正しました。</cmt>
<e type="check" ver="1">In &apos;Explanation for the sake of pro-Japan&apos; by Kim Wansop (2002), the author highly evaluated the Isshinkai&apos;s movement, comparing their movment with a concentration of three revolutionary powers consisted of peasants who tried to reject the oppression of Joseon Dynasty Government (Togaku-to =&gt; Shinpo-kai), the group consisted of revolutionary intellectuals from governing class aimed at modernization of Korea (Ishin-kai) and Japan which tried to secure the &apos;aggressive protection&apos; by supporting the modernization of Korea.</e>
<cmt>人名を英語表記</cmt>
</sen>
</par>
<par id="6">
<sen id="64">
<j>呉善花は、著書『韓国併合への道』で「少なくとも民族の尊厳の確保に賭けて大アジア主義を掲げ、国内で最大限の努力を傾けた李容九らを売国奴と決めつけ、国内で表立った活動をすることもなく外国で抗日活動を展開した安昌浩や李承晩らを愛国者・抗日の闘士と高く評価するバランス・シートは、私にはまったく不当なものである」と評価している。</j>
<e type="trans" ver="1">O Seonhwa placed a mention in her book &apos;Road to the Japan&apos;s annexation of Korea&apos;, saying, &apos;it is completely unreasonable for me that, in a balance-sheet, the persons like 李容九 (이용구) who strived in the country to get back our nation&apos;s dignity aimed at Asianism are regarded as betrayers, while the persons like Ahn Chang-ho and Syngman Rhee (I Seung-man) who rolled out their anti-Japanese activities out of Korea without taking any particular actions in the country are praised as a patriot or anti-Japanese warrior&apos;.</e>
<cmt></cmt>
<e type="trans" ver="2">O Seonhwa placed a mention in her book &apos;Road to the Japan&apos;s annexation of Korea&apos;, saying, &apos;it is completely unreasonable for me that, in a balance-sheet, the persons like 李容九 (이용구) who strived in the country to get back our nation&apos;s dignity aimed at Asianism are regarded as betrayers, while the persons like Ahn Chang-ho and Syngman Rhee (I Seung-man) who rolled out their anti-Japanese activities out of Korea without taking any particular actions in the country are praised as a patriot or anti-Japanese warrior&apos;.</e>
<cmt>修正なし</cmt>
<e type="check" ver="1">O Seonhwa placed a mention in her book &apos;Road to the Japan&apos;s annexation of Korea&apos;, saying, &apos;it is completely unreasonable for me that, in a balance-sheet, the persons like 李容九 (이용구) who strived in the country to get back our nation&apos;s dignity aimed at Asianism are regarded as betrayers, while the persons like Ahn Chang-ho and Syngman Rhee (I Seung-man) who rolled out their anti-Japanese activities out of Korea without taking any particular actions in the country are praised as a patriot or anti-Japanese warrior&apos;.</e>
<cmt>修正なし</cmt>
</sen>
</par>
<par id="7">
<sen id="65">
<j>日本を含めた諸外国の研究者の間では、一進会が大日本帝国の侵略の意図を見抜けず韓国を亡国へと導く役割を果たしたことは事実である。</j>
<e type="trans" ver="1">Many of the world researchers including Japan agreed that it was true that Isshinkai couldn&apos;t see through the intention of invasion Empire of Japan had aimed at and happened to play a role for leading Korea to the ruin.</e>
<cmt>このセルと下のセルはもともと二つに分割してありましたが、内容が不適切なところで分割してあったので、適切と思われるところで分割しなおしました。</cmt>
<e type="trans" ver="2">Many of the world researchers including Japan agreed that it was true that Isshinkai couldn&apos;t see through the intention of invasion Empire of Japan had aimed at and happened to play a role for leading Korea to the ruin.</e>
<cmt>修正なし</cmt>
<e type="check" ver="1">Many of the world researchers including Japan agreed that it was true that Isshinkai couldn&apos;t see through the intention of invasion Empire of Japan had aimed at and happened to play a role for leading Korea to the ruin.</e>
<cmt>修正なし</cmt>
</sen>
<sen id="66">
<j>しかし、対等合併論自体は日本の朝鮮併合論（朝鮮が日本に従属し、主権を放棄する形で植民地となる。）とは明らかに異なり、寧ろ併合後の日本が一進会すらも用済みとして切捨て、植民地統治を開始したことを踏まえて、「一進会もまた犠牲者であり、必ずしも責められるべき点ばかりではなかった」とする同情的意見も強い。</j>
<e type="trans" ver="1">But the theory as to the equal consolidation itself was clearly different from that of Japan&apos;s annexation of Korea (Korea is supposed to depend on Japan and be colonized abandonning their sovereignty), rather, taking into account the fact that Japan cut off even Isshinkai as a worn-out after the annexation and launched the colonial domination, many of the researchers also have a sympathey that &apos;Isshinkai is also one of victims and what they did is not necessarily accusable&apos;.</e>
<cmt></cmt>
<e type="trans" ver="2">But the theory as to the equal consolidation itself was clearly different from that of Japan&apos;s annexation of Korea (Korea is supposed to depend on Japan and be colonized abandonning their sovereignty), rather, taking into account the fact that Japan cut off even Isshinkai as a worn-out after the annexation and launched the colonial domination, many of the researchers also have a sympathy that &apos;Isshinkai is also one of victims and what they did is not necessarily accusable&apos;.</e>
<cmt>sympatheyのスペルミスを修正しました。</cmt>
<e type="check" ver="1">But the theory as to the equal consolidation itself was clearly different from that of Japan&apos;s annexation of Korea (Korea is supposed to depend on Japan and be colonized abandonning their sovereignty), rather, taking into account the fact that Japan cut off even Isshinkai as a worn-out after the annexation and launched the colonial domination, many of the researchers also have a sympathy that &apos;Isshinkai is also one of victims and what they did is not necessarily accusable&apos;.</e>
<cmt>修正なし</cmt>
</sen>
</par>
</sec>
<copyright>copyright (c) 2010 Amanatsu(id:65486), Straysheep(id:42448), Jjok(id:55405), 阿修羅(id:29454), Bellcricket(id:37640), ParkAve3(id:101015), Jomasa(id:297040), Qazzx(id:8772), Ddgo(id:261079), Greenland4(id:114494), Uraios(id:72687), YAMAARASHI(id:18211), 磯多申紋(id:36455), Commonsenses(id:11185), Dondokken(id:246411), Real Madrid(id:27490), Wkpda(id:50685), Chocopa(id:2222), Chichiii(id:242358), Tsubame-ex(id:53988), Tatsujin28(id:9300), NAZONAZO(id:110613), スススス(id:119930), Nichetas(id:65887), Race(id:131322), 果心居士(id:248111), Nakchipallang(id:71476), Knightofathena(id:19058), Lucas0123(id:130266), Clarin(id:60278), RoboDick(id:34097), Mahoroba(id:23616), ΑΩ(id:197298), NDR(id:5500), 「あなたには関係ない」(id:49400), カタバミ(id:142235), 独立行政法人情報通信研究機構．このテキストの利用はCreative Commons Attribution-Share-Alike License 3.0 の条件の下に許諾されます．（この著作権者一覧には、Wikipedia IPユーザーを含んでおりません．この点に関するお問い合わせはこちらまで：kyoto-corpus@khn.nict.go.jp）</copyright>
</art>